Workbook

Sheet README
A1: Chaos Engineering Scenario Catalog
A2: Audience: Sr. technical leadership (program review) and the Chaos Engineering team (execution). Derived from code-based assessment artifacts, C1–C4/EAC diagrams, the recon (DTR) pipeline diagram/narrative, and prior FMEA / timeout-chain / DR work. Nothing in the catalog is invented beyond those sources; unknowns are flagged in Open Items.
A4: Sheets
A5: 1. Service Inventory | B5: The 17 Core services with archetype, DR posture, ingress, data stores, RDS Proxy status, dependencies and scheduled jobs. Source of truth for scenario targeting.
A6: 2. Scenario Catalog | B6: The full experiment catalog. One row per scenario. Filter by Wave, Fault Domain, Archetype, Target Service or Injection Plane.
A7: 3. Priority Model | B7: Scoring definitions for Likelihood and Severity, and how Priority and Wave assignment work.
A8: 4. Wave Plan | B8: Execution waves with theme, entry/exit criteria and live scenario counts.
A9: 5. Coverage Matrix | B9: Fault Domain × Wave and Fault Domain × Injection Plane counts, computed live from the catalog.
A10: 6. Open Items | B10: Unknowns, confirmations pending, and documentation gaps that gate specific scenarios.
A11: 7. App Scan Instructions | B11: Durable method for scanning any application repo (Maven multi-module) for resilience-relevant facts: dependency/version census, resilience config, timeout chain, retry amplification inputs, Kafka consumer config, idempotency evidence, anti-pattern sweep, and perf-vs-prod profile diff. Re-runnable on future services unchanged.
A12: 8. Infra Scan Instructions | B12: Durable method for discovering cloud components from infrastructure-as-code (tool-agnostic: Terraform/CDK/CloudFormation/Serverless), reconciling them against the Service Inventory tab, and onboarding new AWS components/services into the taxonomy going forward.
A14: Key concepts
A15: Injection plane | B15: Infrastructure = fault injected below the app (FIS, network, AWS resources). Application = fault injected inside the request path (latency/exceptions/errors via app-level tooling or a proxy). Compound = multiple simultaneous faults. Detection = the hypothesis is about observability, not recovery.
A16: Dual success criteria | B16: Every scenario has TWO pass conditions: the system behaved as hypothesized AND the fault was detected/alerted correctly (Dynatrace + CloudWatch). A fault that recovers silently is a FAILED experiment. Detection baseline scenarios (CE-OBS-*) run in Wave 1 for this reason.
A17: PERF validity | B17: High = result transfers to PROD with confidence. Medium = transfers with caveats (capacity/data-volume/config deltas). Low = PERF result is indicative only; needs eventual PROD validation or explicit delta analysis.
A18: Steady state first | B18: A scenario is not runnable until its steady-state signal exists and is trusted. If the SLI/dashboard for the hypothesis is missing or unvalidated, that is itself a Wave-1 finding.
A20: How to use (chaos team)
A21: Cells to fill in | B21: YELLOW cells are yours to populate: FMEA Ref (map each scenario to the existing FMEA scenario IDs — ASSESSED items first), Journeys (which of the 16 official journeys the scenario exercises), and Status as work progresses (Proposed → Ready → Executed → Confirmed / Finding).
A22: Example of a filled row | B22: CE-COM-01 carries example values in its FMEA Ref and Journeys cells (marked 'EXAMPLE —') showing the expected format. Replace with real IDs.
A23: Prerequisites | B23: Prereq IDs = scenarios that must be Confirmed before this one is meaningful (singles before compounds). Waves are sequenced so prerequisites always land in an earlier or same wave.
A24: Governance | B24: Wave 1–2 run in PERF game days with evidence capture per run. Wave 3–4 include coordination-heavy and DR drills; treat each as a scheduled event with stakeholder sign-off. Production experimentation is out of scope for this catalog version.

Sheet Service Inventory
A1: # | B1: Service | C1: Acronym | D1: APG | E1: Archetype | F1: DR Posture | G1: Ingress | H1: Data Stores | I1: RDS Proxy | J1: Core-internal Sync Deps | K1: External Sync Deps | L1: Async Produces / Consumes | M1: Scheduled Jobs | N1: Doc Status / Notes
A2: 1 | B2: Account Locator Component | C2: ALS | D2: LOCR | E2: Sync API + batch extract — mixed | F2: Active/Active (latency routing) | G2: R53→NLB→API GW→NLB→ALB→ECS | H2: Aurora (direct), ElastiCache, S3 (RDS→S3 Lambda) | I2: No (direct) | J2: ACL (Register) | K2: Inbound only (ARR/FAP/DCPA/DCP/Payments/SPG/OCS) | L2: Prod: Locator Event→MBUS→Datalake; Batch: Lambda→S3→MFT→EDX | M2: Batch extract | N2: OK
A3: 2 | B3: Account Reference Management | C3: ARM | D3: ACCT | E3: Sync API | F3: Active/Active | G3: R53→NLB→API GW→NLB→ALB→ECS | H3: Aurora (direct), ElastiCache | I3: No (direct) | J3: Inbound only (SAM/AFM/DBE/DTE/DSM/DCM) | K3: none | L3: none shown | M3: none | N3: OK
A4: 3 | B4: Core Account Management | C4: SAM | D4: ACCT | E4: Orchestrator (acct lifecycle) — mixed | F4: Active/Passive | G4: R53→NLB→API GW→NLB→ALB→ECS (from SMB/ARR) | H4: Aurora (direct — Core DB) | I4: No (direct) | J4: ALS, ARM, AFM, ACL | K4: CBS (Account Mgmt) | L4: Prod: Core Acct Change→MBUS→Datalake; Cons: MBUS incl. RECN EOD Completion | M4: none | N4: OK
A5: 4 | B5: Account Feature Management | C5: AFM | D5: ACCT | E5: Sync API + event publisher — mixed | F5: Active/Passive | G5: R53→NLB→API GW→NLB→ALB→ECS (from SAM) | H5: Aurora (direct — AFM DB), ElastiCache | I5: No (direct) | J5: MCC, DBE, DSM, DCM, ARM, ACL | K5: CBS Posting, CBS Transaction | L5: Prod: Feature State Change→MBUS (→DCP-TA, Datalake) | M5: none | N5: OK
A6: 5 | B6: Account Locator Admin Tool | C6: DLAT | D6: LOCR | E6: Not shown (infra diagram only) | F6: Active/Passive (per rule) | G6: R53→NLB→ALB→ECS — NO API GW | H6: Aurora (direct), S3 | I6: No (direct) | J6: not shown | K6: not shown | L6: not shown | M6: none | N6: GAP — dependencies undocumented
A7: 6 | B7: Attribute Change Log | C7: ACL | D7: ACCT | E7: Event aggregator/consumer + Sync API — mixed | F7: Active/Passive (per rule) | G7: R53→NLB→API GW→NLB→ALB→ECS | H7: Aurora (direct — History Datastore) | I7: No (direct) | J7: Receives SAM/AFM/ALS registrations | K7: none | L7: Cons: Core Acct Change, Feature Change (SAM/AFM/ALS) | M7: none | N7: OK
A8: 7 | B8: Core Subledger Management | C8: DSM | D8: REFD | E8: Sync API + event publisher — mixed | F8: Active/Passive; cross-region repl., bidirectional Aurora | G8: External NLB→API GW→Internal NLB→ALB→ECS Anywhere | H8: Aurora (direct — writer/reader nodes), IN-MEMORY HASHMAP | I8: No (direct) | J8: MCC, ARM (migration lookup) | K8: CBS (Subledger+RoutingRule, Balance Inquiry), Payments/MMS | L8: Prod: Subledger CUD→MBUS→AU+Continuum/DataLake; +Migration Topic | M8: none | N8: In-memory state — see CE-COM-05
A9: 8 | B9: Spend-Track Experience Svc | C9: SSE | D9: REFD | E9: No diagram provided | F9: 3-Active (+us-west-2, stateless per rule) | G9: no diagram | H9: no diagram | I9: TBC | J9: no diagram | K9: no diagram | L9: no diagram | M9: none | N9: GAP — no artifact at all; scenarios blocked
A10: 9 | B10: Tasks Experience Svc | C10: CHE | D10: ENRC | E10: Edge/BFF | F10: 3-Active (+us-west-2, stateless) | G10: Via DPS Proxy/Digital; shares 900069 ingress | H10: none of its own shown | I10: n/a | J10: DCM (Task Inquiry for Nudges), MCC (Spend Categories) | K10: none shown | L10: none shown | M10: none | N10: Reconstructed from other diagrams
A11: 10 | B11: Transaction Experience Svc | C11: TE | D11: ALRT | E11: Edge/BFF | F11: 3-Active (+us-west-2) | G11: Akamai→CTC→DPS Proxy→Transit GW→R53→API GW (AuthAnywhere token validate)→NLB→ALB→ECS | H11: none (stateless) | I11: n/a | J11: none | K11: ChannelContext, ETU/TU Transactions, GKP on-prem via Envoy, AuthAnywhere | L11: none shown | M11: none | N11: OK
A12: 11 | B12: MCC Data Management Svc | C12: MCC | D12: REFD | E12: Sync API (ref data) + scheduled pipeline — mixed | F12: Active/Passive; DR: PILOT LIGHT | G12: API GW→NLB→ALB→ECS (+ On-Prem API GW); EventBridge scheduler (ETU pull) | H12: Aurora (direct — Local Data Store), S3 (config) | I12: No (direct) | J12: Inbound only (DSM, SAM/Acct Creation, Tasks Exp) | K12: ETU (GET Reference Data, scheduled) | L12: Scheduler-triggered ETU pull; writes config→S3; no Kafka publish | M12: EventBridge ETU pull | N12: OK
A13: 12 | B13: Core Task Management | C13: DCM | D13: ENRC | E13: Sync API (CRUD) + event publisher + scheduled job — mixed | F13: Active/Passive (Warm Standby) | G13: Via DPS Proxy/Digital & Banking Payments→NLB→NLB→ALB (+API GW Regional Endpt); weekly-job scheduler via SQS | H13: Aurora (RDS PROXY, separate Global cluster), ElastiCache (shared), SQS+DLQ | I13: YES | J13: ARM, SAM, Core Alerts (DCC 900070) | K13: CBS (posting/balance inquiry via Digital Payments) | L13: Prod: Task Life Cycle→MBUS (→Alerts, DTE); SQS: weekly future-task job | M13: Weekly SQS-driven job | N13: OK
... A18: 17 | B18: Core Alerts | C18: DAL | D18: ALRT | E18: Event processor + API intake — mixed | F18: Active/Passive | G18: Kafka (Enriched Txn CUD, Task Lifecycle, D2 Alert Topic) + API; CRON scheduler (failure recovery); API GW/NLB/ALB/R53 | H18: Aurora (direct — Alerts DB / RDS Global) | I18: No (direct) | J18: none | K18: CSU (Fetch Parent/Child, payload enrichment) | L18: Cons: Enriched Txn CUD + Task Lifecycle. Prod: enriched alerts→Notify Alert Topic→NOTIFY | M18: Cron (failure recovery) | N18: OK

Sheet Scenario Catalog
A1: ID | B1: Scenario | C1: Fault Domain | D1: Injection Plane | E1: Archetype(s) | F1: Target Service(s) | G1: Fault / Injection | H1: Hypothesis (steady state holds if…) | I1: Tooling / Method | J1: Blast Radius | K1: Abort Condition | L1: Success — System | M1: Success — Detection | N1: PERF Validity | O1: PERF Note | P1: Likelihood (1-5) | Q1: Severity (1-5) | R1: Priority | S1: Wave | T1: Prereq IDs | U1: FMEA Ref (FILL) | V1: Journeys (FILL) | W1: Status | X1: Likelihood Tier | Y1: Risk Rating
A2: CE-COM-01 | B2: Single Fargate task termination — sync API | C2: Compute | D2: Infrastructure | E2: Sync API | F2: SAM (repeat per sync API) | G2: Terminate 1 running task of the service under steady synthetic load. | H2: ECS replaces the task; ALB deregisters/drains; journey SLI stays within SLO; zero 5xx beyond in-flight requests. | I2: FIS aws:ecs:stop-task | J2: Single task | K2: SLI breach > 2 min | L2: Task replaced ≤ target time; no request loss beyond in-flight; connection re-establishment clean. | M2: Dynatrace detects task churn; no false-positive paging for single-task events (noise calibration). | N2: High | O2: Recovery mechanics transfer; scaled-down task counts change % impact only. | P2: 4 | Q2: 2 | R2: =P2*Q2 | S2: 1 | U2: EXAMPLE — FMEA-ECS-004, FMEA-ECS-011 | V2: EXAMPLE — J03, J07 | W2: Proposed | X2: =IF(P2=5,"Almost Certain",IF(P2=4,"Likely",IF(P2=3,"Possible",IF(P2=2,"Unlikely","Rare")))) | Y2: =IF(R2>=16,"Critical",IF(R2>=9,"High",IF(R2>=4,"Medium","Opportunistic")))
A3: CE-COM-02 | B3: Bulk task termination (50%) under load | C3: Compute | D3: Infrastructure | E3: Sync API | F3: ARM, SAM | G3: Terminate 50% of tasks simultaneously under load. | H3: Remaining tasks absorb load without pool/thread exhaustion; scale-out restores capacity; SLI degrades within tolerated bounds. | I3: FIS aws:ecs:stop-task (percentage) | J3: One service | K3: Error rate >5% for >3 min | L3: No cascading failure to callers; scale-out completes; queuing recovers. | M3: Capacity alarm fires; Dynatrace shows saturation before errors. | N3: Medium | O3: PERF task counts/scaling policies differ from PROD — % result indicative only. | P3: 3 | Q3: 3 | R3: =P3*Q3 | S3: 1 | T3: CE-COM-01 | W3: Proposed | X3: =IF(P3=5,"Almost Certain",IF(P3=4,"Likely",IF(P3=3,"Possible",IF(P3=2,"Unlikely","Rare")))) | Y3: =IF(R3>=16,"Critical",IF(R3>=9,"High",IF(R3>=4,"Medium","Opportunistic")))
A4: CE-COM-03 | B4: Task kill during rolling deployment | C4: Compute | D4: Infrastructure | E4: Sync API | F4: One sync API | G4: Inject task termination while a deployment is replacing tasks. | H4: Deployment circuit breaker / min-healthy settings prevent capacity dropping below safe floor; rollback triggers if needed. | I4: FIS + pipeline coordination | J4: One service | K4: Healthy count < min for >2 min | L4: No dual-capacity loss; deploy completes or rolls back cleanly. | M4: Deploy-time alerting distinguishes deployment churn from failure. | N4: High | O4: Deployment config parity assumed — verify. | P4: 3 | Q4: 3 | R4: =P4*Q4 | S4: 2 | T4: CE-COM-01 | W4: Proposed | X4: =IF(P4=5,"Almost Certain",IF(P4=4,"Likely",IF(P4=3,"Possible",IF(P4=2,"Unlikely","Rare")))) | Y4: =IF(R4>=16,"Critical",IF(R4>=9,"High",IF(R4>=4,"Medium","Opportunistic")))
A5: CE-COM-04 | B5: Event-processor task kill mid-consumption | C5: Compute | D5: Infrastructure | E5: Event processor | F5: DBE, DTE | G5: Kill a consumer task while it processes a batch of CBS events. | H5: Offsets uncommitted messages are redelivered; enrichment is idempotent — no lost and no duplicate enriched events downstream (AU/ETU). | I5: FIS aws:ecs:stop-task | J5: One consumer group member | K5: Consumer lag > threshold, no drain | L5: Rebalance completes; redelivered messages produce identical enriched output exactly once (effective). | M5: Lag + rebalance visible in Dynatrace; DLQ/poison alarms silent. | N5: High | O5: Idempotency logic is environment-independent. | P5: 4 | Q5: 4 | R5: =P5*Q5 | S5: 1 | W5: Proposed | X5: =IF(P5=5,"Almost Certain",IF(P5=4,"Likely",IF(P5=3,"Possible",IF(P5=2,"Unlikely","Rare")))) | Y5: =IF(R5>=16,"Critical",IF(R5>=9,"High",IF(R5>=4,"Medium","Opportunistic")))
A6: CE-COM-05 | B6: DSM task recycle — in-memory hashmap loss | C6: Compute | D6: Infrastructure | E6: Sync API (stateful) | F6: DSM (+DSC warmer) | G6: Recycle DSM tasks; measure window where in-memory subledger map is cold before DSC/ElastiCache warm state is usable. | H6: DSM serves correct responses during warm-up (falls back to Aurora/ElastiCache) with bounded latency penalty; no wrong answers from empty map. | I6: FIS aws:ecs:stop-task | J6: DSM only | K6: Incorrect subledger responses | L6: Zero correctness violations; warm-up window quantified; fallback path exercised. | M6: Warm-up window observable as metric; DSC warmer health alarmed. | N6: High | O6: Pattern risk is design-level, not capacity-level. | P6: 4 | Q6: 4 | R6: =P6*Q6 | S6: 1 | W6: Proposed | X6: =IF(P6=5,"Almost Certain",IF(P6=4,"Likely",IF(P6=3,"Possible",IF(P6=2,"Unlikely","Rare")))) | Y6: =IF(R6>=16,"Critical",IF(R6>=9,"High",IF(R6>=4,"Medium","Opportunistic")))
A7: CE-COM-06 | B7: ECR image pull failure during scale-out | C7: Compute | D7: Infrastructure | E7: Any | F7: One sync API | G7: Block image pulls (registry deny / endpoint block in PERF) then force scale-out. | H7: Existing tasks keep serving; scale-out failure is alarmed; no flapping replacement loop kills healthy capacity. | I7: Custom (endpoint/registry policy) | J7: One service | K7: Healthy capacity shrinking | L7: Steady state maintained on existing tasks; clear failure signal. | M7: Scale-out failure alarm exists and fires (suspected gap). | N7: High | O7: — | P7: 2 | Q7: 3 | R7: =P7*Q7 | S7: 2 | W7: Proposed | X7: =IF(P7=5,"Almost Certain",IF(P7=4,"Likely",IF(P7=3,"Possible",IF(P7=2,"Unlikely","Rare")))) | Y7: =IF(R7>=16,"Critical",IF(R7>=9,"High",IF(R7>=4,"Medium","Opportunistic")))
A8: CE-COM-07 | B8: Memory pressure → container OOM behavior | C8: Resource | D8: Application | E8: Sync API | F8: One JVM service | G8: Drive heap growth via app-level memory assault until container limit. | H8: OOM kill is clean (task replaced) rather than gray degradation; no long GC-driven brownout serving errors. | I8: App-level (Chaos Monkey for Spring Boot / stress endpoint) | J8: One task | K8: SLI breach | L8: Fail-fast behavior; replacement clean; heap/GC limits tuned. | M8: GC/heap alerting catches degradation BEFORE OOM. | N8: High | O8: JVM behavior transfers. | P8: 3 | Q8: 3 | R8: =P8*Q8 | S8: 2 | T8: CE-COM-01 | W8: Proposed | X8: =IF(P8=5,"Almost Certain",IF(P8=4,"Likely",IF(P8=3,"Possible",IF(P8=2,"Unlikely","Rare")))) | Y8: =IF(R8>=16,"Critical",IF(R8>=9,"High",IF(R8>=4,"Medium","Opportunistic")))
A9: CE-COM-08 | B9: Scheduled-job duplicate / missed execution | C9: Compute | D9: Application | E9: Scheduled job | F9: DCM weekly job, MCC ETU pull, DAL cron | G9: Run service at >1 task through a scheduled window; separately kill task at trigger time. | H9: Job fires exactly once per window (locking/leader election proven); a missed window is detected and recovered per design. | I9: Scale/kill + job observation | J9: Job outputs | K9: Duplicate side-effects detected | L9: No duplicate task-job effects / double ETU pull / double alert recovery; missed-window path defined. | M9: Missed or duplicate execution alarms (suspected gap for all three). | N9: High | O9: Logic-level, environment-independent. | P9: 3 | Q9: 4 | R9: =P9*Q9 | S9: 1 | W9: Proposed | X9: =IF(P9=5,"Almost Certain",IF(P9=4,"Likely",IF(P9=3,"Possible",IF(P9=2,"Unlikely","Rare")))) | Y9: =IF(R9>=16,"Critical",IF(R9>=9,"High",IF(R9>=4,"Medium","Opportunistic")))
A10: CE-DB-01 | B10: Aurora writer failover — RDS-Proxy-fronted | C10: Data-Aurora | D10: Infrastructure | E10: Mixed (ENRC) | F10: DCM, DBE, DTE | G10: Trigger in-region writer failover on the proxy-fronted cluster under load. | H10: RDS Proxy preserves/pins client connections; app-visible impact limited to brief write latency; no connection storm. | I10: FIS aws:rds / failover-db-cluster | J10: ENRC cluster | K10: Error rate >5% / 3 min | L10: Failover ≤ target; HikariCP pools stable; writes resume without app restarts. | M10: DB failover event alarmed; Dynatrace DB-layer signal correct. | N10: Medium | O10: Instance class + data volume affect failover duration. | P10: 3 | Q10: 4 | R10: =P10*Q10 | S10: 1 | W10: Proposed | X10: =IF(P10=5,"Almost Certain",IF(P10=4,"Likely",IF(P10=3,"Possible",IF(P10=2,"Unlikely","Rare")))) | Y10: =IF(R10>=16,"Critical",IF(R10>=9,"High",IF(R10>=4,"Medium","Opportunistic")))
A11: CE-DB-02 | B11: Aurora writer failover — direct-connection | C11: Data-Aurora | D11: Infrastructure | E11: Sync API | F11: SAM (Core DB) | G11: Same failover on a direct (non-proxy) cluster under load. | H11: aws-jdbc-wrapper fast-failover redirects connections within pool timeout budget; documented behavior matches FMEA ledger. | I11: FIS / failover-db-cluster | J11: Core DB cluster | K11: Error rate >5% / 3 min | L11: Recovery time quantified; asymmetry vs CE-DB-01 documented as evidence for proxy adoption decision. | M11: Same detection as DB-01. | N11: Medium | O11: Same caveats as DB-01. | P11: 3 | Q11: 4 | R11: =P11*Q11 | S11: 1 | T11: CE-DB-01 | W11: Proposed | X11: =IF(P11=5,"Almost Certain",IF(P11=4,"Likely",IF(P11=3,"Possible",IF(P11=2,"Unlikely","Rare")))) | Y11: =IF(R11>=16,"Critical",IF(R11>=9,"High",IF(R11>=4,"Medium","Opportunistic")))
A12: CE-DB-03 | B12: Connection storm on writer promotion | C12: Data-Aurora | D12: Compound | E12: Sync API | F12: SAM + heaviest callers | G12: Writer failover while pools are near max and load is high — deliberate worst case. | H12: HikariCP settings (max pool, connection timeout, validation) prevent thundering-herd reconnect storm from delaying promotion recovery. | I12: FIS + load profile | J12: Core DB + callers | K12: DB CPU pegged >5 min | L12: Reconnect ramp controlled; total brownout window within FMEA-assessed bound. | M12: Pool saturation metrics visible pre-failure. | N12: Low | O12: Pool sizes & instance class differ in PERF — directional only; flag for PROD-parity retest. | P12: 2 | Q12: 5 | R12: =P12*Q12 | S12: 3 | T12: CE-DB-02,CE-APP-05 | W12: Proposed | X12: =IF(P12=5,"Almost Certain",IF(P12=4,"Likely",IF(P12=3,"Possible",IF(P12=2,"Unlikely","Rare")))) | Y12: =IF(R12>=16,"Critical",IF(R12>=9,"High",IF(R12>=4,"Medium","Opportunistic")))
A13: CE-DB-04 | B13: Reader node failure (reader/writer split) | C13: Data-Aurora | D13: Infrastructure | E13: Sync API | F13: Proxy-fronted ENRC services | G13: Kill/reboot a reader instance under read-heavy load. | H13: Reads redistribute to surviving readers/writer without error spike; reader endpoint DNS behavior within TTL budget. | I13: FIS aws:rds:reboot-db-instances | J13: One reader | K13: Read errors sustained | L13: Read continuity; latency bump bounded. | M13: Reader loss alarmed distinctly from writer events. | N13: High | O13: — | P13: 3 | Q13: 3 | R13: =P13*Q13 | S13: 2 | T13: CE-DB-01 | W13: Proposed | X13: =IF(P13=5,"Almost Certain",IF(P13=4,"Likely",IF(P13=3,"Possible",IF(P13=2,"Unlikely","Rare")))) | Y13: =IF(R13>=16,"Critical",IF(R13>=9,"High",IF(R13>=4,"Medium","Opportunistic")))
A14: CE-DB-05 | B14: Global replication lag / stale-read tolerance | C14: Data-Aurora | D14: Infrastructure | E14: All Aurora users | F14: Global clusters | G14: Induce/observe elevated cross-region replication lag (heavy write load; direct lag injection has no FIS action — method gap). | H14: Services and DR runbooks tolerate documented lag; RPO assumptions (incl. DBE 'RPO PoF') hold under stress. | I14: Custom (write-load driven) | J14: Secondary region reads | K14: Lag beyond RPO assumption | L14: Measured lag vs documented RPO; consumers of secondary data behave. | M14: Replication-lag alarm exists with correct threshold. | N14: Low | O14: Data volume in PERF understates PROD lag — treat as method validation. | P14: 2 | Q14: 4 | R14: =P14*Q14 | S14: 3 | W14: Proposed | X14: =IF(P14=5,"Almost Certain",IF(P14=4,"Likely",IF(P14=3,"Possible",IF(P14=2,"Unlikely","Rare")))) | Y14: =IF(R14>=16,"Critical",IF(R14>=9,"High",IF(R14>=4,"Medium","Opportunistic")))
A15: CE-DB-06 | B15: Managed planned global failover | C15: Data-Aurora | D15: Infrastructure | E15: All | F15: Aurora Global (per cluster) | G15: Execute managed planned failover us-east-1→us-east-2. | H15: Failover completes within documented window; applications reconnect to new writer; replication reverses cleanly. | I15: AWS managed operation | J15: One global cluster | K15: Failback risk identified | L15: End-to-end timing evidence per cluster; app reconnect behavior per proxy/direct split. | M15: Region-level DB alarms coherent during transition. | N15: Medium | O15: Cluster sizing deltas. | P15: 2 | Q15: 4 | R15: =P15*Q15 | S15: 3 | T15: CE-DB-01,CE-DB-02 | W15: Proposed | X15: =IF(P15=5,"Almost Certain",IF(P15=4,"Likely",IF(P15=3,"Possible",IF(P15=2,"Unlikely","Rare")))) | Y15: =IF(R15>=16,"Critical",IF(R15>=9,"High",IF(R15>=4,"Medium","Opportunistic")))
A16: CE-DB-07 | B16: Unplanned global failover (detach & promote) | C16: Data-Aurora | D16: Infrastructure | E16: All | F16: Aurora Global (per cluster) | G16: Simulate region loss: detach secondary and promote (drill). | H16: Promotion + app cutover meets RTO; data loss within RPO; procedure executable by on-call from runbook alone. | I16: Drill (manual/scripted) | J16: One global cluster + dependents | K16: Any ambiguity in runbook | L16: RTO/RPO evidence; stale-writer protection confirmed (see DB-08). | M16: All failover alarms/dashboards correct in surviving region. | N16: Low | O16: PERF topology parity required; data volume affects timing. | P16: 1 | Q16: 5 | R16: =P16*Q16 | S16: 4 | T16: CE-DB-06 | W16: Proposed | X16: =IF(P16=5,"Almost Certain",IF(P16=4,"Likely",IF(P16=3,"Possible",IF(P16=2,"Unlikely","Rare")))) | Y16: =IF(R16>=16,"Critical",IF(R16>=9,"High",IF(R16>=4,"Medium","Opportunistic")))
A17: CE-DB-08 | B17: Stale writer endpoint after promotion | C17: Data-Aurora | D17: Application | E17: All Aurora users | F17: Sample per driver config | G17: After promotion, verify no service continues writing to old-region endpoint (driver DNS caching, wrapper topology refresh). | H17: aws-jdbc-wrapper topology awareness prevents split-brain writes; any cached-endpoint writes fail closed. | I17: Post-drill verification + custom probe | J17: Data integrity | K17: Any write accepted by old writer | L17: Zero writes to demoted writer; wrapper refresh timing quantified. | M17: Cross-region write-attempt visibility exists (likely gap). | N17: High | O17: Driver behavior transfers. | P17: 2 | Q17: 5 | R17: =P17*Q17 | S17: 3 | T17: CE-DB-06 | W17: Proposed | X17: =IF(P17=5,"Almost Certain",IF(P17=4,"Likely",IF(P17=3,"Possible",IF(P17=2,"Unlikely","Rare")))) | Y17: =IF(R17>=16,"Critical",IF(R17>=9,"High",IF(R17>=4,"Medium","Opportunistic")))
A18: CE-DB-09 | B18: IAM auth token failure (aws-jdbc-wrapper) | C18: Data-Aurora | D18: Infrastructure | E18: All (no static DB passwords) | F18: One sync API | G18: Deny IAM DB-auth token generation (perf-scoped IAM policy) for the service role. | H18: Existing connections continue (token is connect-time only); NEW connections fail with clear error; pool contraction is alarmed before exhaustion. | I18: Custom (IAM deny in PERF) | J18: One service's new connections | K18: Full pool exhaustion | L18: Degradation curve understood; recovery instant on policy restore. | M18: Auth-failure signature distinct in logs/alerts vs generic DB errors. | N18: High | O18: IAM mechanics identical across envs. | P18: 2 | Q18: 4 | R18: =P18*Q18 | S18: 2 | W18: Proposed | X18: =IF(P18=5,"Almost Certain",IF(P18=4,"Likely",IF(P18=3,"Possible",IF(P18=2,"Unlikely","Rare")))) | Y18: =IF(R18>=16,"Critical",IF(R18>=9,"High",IF(R18>=4,"Medium","Opportunistic")))
A19: CE-DB-10 | B19: RDS Proxy endpoint unavailability | C19: Data-Aurora | D19: Infrastructure | E19: Mixed (ENRC) | F19: DCM, DBE, DTE | G19: Block proxy endpoint (SG/NACL in PERF) — the proxy as its own failure point. | H19: Services fail fast per timeout chain (no hang); recovery on restore without restart; proxy-as-SPOF risk quantified for the 3 ENRC services. | I19: Custom (network deny) | J19: ENRC DB access | K19: Hang > timeout budget | L19: Timeout chain honors documented order; no thread pile-up. | M19: Proxy health distinct from cluster health in monitoring. | N19: High | O19: — | P19: 2 | Q19: 4 | R19: =P19*Q19 | S19: 2 | T19: CE-EDGE-01 | W19: Proposed | X19: =IF(P19=5,"Almost Certain",IF(P19=4,"Likely",IF(P19=3,"Possible",IF(P19=2,"Unlikely","Rare")))) | Y19: =IF(R19>=16,"Critical",IF(R19>=9,"High",IF(R19>=4,"Medium","Opportunistic")))
A20: CE-CACHE-01 | B20: ElastiCache primary failover | C20: Cache | D20: Infrastructure | E20: Sync API / Event processor | F20: Shared cluster users (ARM, AFM, DBE, DTE, DCM) | G20: Fail over primary→replica on the shared Redis cluster. | H20: Clients reconnect within seconds; brief error/latency blip absorbed by callers; no data-correctness impact. | I20: FIS aws:elasticache / console failover | J20: Shared cache | K20: Errors sustained >2 min | L20: Reconnect clean; SLI blip bounded. | M20: Cache failover event alarmed. | N20: High | O20: — | P20: 3 | Q20: 3 | R20: =P20*Q20 | S20: 1 | W20: Proposed | X20: =IF(P20=5,"Almost Certain",IF(P20=4,"Likely",IF(P20=3,"Possible",IF(P20=2,"Unlikely","Rare")))) | Y20: =IF(R20>=16,"Critical",IF(R20>=9,"High",IF(R20>=4,"Medium","Opportunistic")))
A21: CE-CACHE-02 | B21: Full cache cluster unavailable | C21: Cache | D21: Infrastructure | E21: Sync API | F21: ARM, AFM (cache-dependent APIs) | G21: Block all access to Redis for the service under load. | H21: Services degrade to Aurora-backed path (or defined degraded mode) — slower but correct; Aurora absorbs amplified read load. | I21: Custom (SG deny) | J21: Cache-dependent services | K21: Aurora saturation | L21: Correctness preserved; amplification factor measured (input to CE-CMP-05). | M21: Cache-down + DB-amplification both visible. | N21: Medium | O21: Aurora headroom differs in PERF — amplification ratio transfers, absolute capacity doesn't. | P21: 2 | Q21: 4 | R21: =P21*Q21 | S21: 2 | T21: CE-CACHE-01 | W21: Proposed | X21: =IF(P21=5,"Almost Certain",IF(P21=4,"Likely",IF(P21=3,"Possible",IF(P21=2,"Unlikely","Rare")))) | Y21: =IF(R21>=16,"Critical",IF(R21>=9,"High",IF(R21>=4,"Medium","Opportunistic")))
A22: CE-CACHE-03 | B22: Cache auth token retrieval failure (VaultSM ASM) | C22: Cache | D22: Infrastructure | E22: All cache users | F22: One service | G22: Deny ASM secret retrieval for Redis auth token; include a task recycle during the outage. | H22: Running tasks unaffected (token held); RECYCLED tasks fail startup loudly, not silently degraded; no crash-loop masking. | I22: Custom (ASM deny in PERF) | J22: One service | K22: Silent degraded serving | L22: Startup-dependency risk quantified; crash-loop backoff sane. | M22: Secret-retrieval failure alarmed distinctly. | N22: High | O22: — | P22: 2 | Q22: 4 | R22: =P22*Q22 | S22: 2 | W22: Proposed | X22: =IF(P22=5,"Almost Certain",IF(P22=4,"Likely",IF(P22=3,"Possible",IF(P22=2,"Unlikely","Rare")))) | Y22: =IF(R22>=16,"Critical",IF(R22>=9,"High",IF(R22>=4,"Medium","Opportunistic")))
A23: CE-CACHE-04 | B23: Cold-cache stampede | C23: Cache | D23: Infrastructure | E23: Sync API | F23: ARM/AFM + Aurora | G23: Flush cache under load; measure stampede onto Aurora. | H23: Request coalescing / TTL jitter / warmer limits stampede; Aurora load stays under safe threshold. | I23: Custom (FLUSH in PERF) | J23: Cache + backing DB | K23: Aurora saturation | L23: Stampede controls proven or gap documented. | M23: Amplification visible as leading indicator. | N23: Medium | O23: Absolute DB capacity differs. | P23: 3 | Q23: 4 | R23: =P23*Q23 | S23: 2 | T23: CE-CACHE-02 | W23: Proposed | X23: =IF(P23=5,"Almost Certain",IF(P23=4,"Likely",IF(P23=3,"Possible",IF(P23=2,"Unlikely","Rare")))) | Y23: =IF(R23>=16,"Critical",IF(R23>=9,"High",IF(R23>=4,"Medium","Opportunistic")))
A24: CE-CACHE-05 | B24: ElastiCache loss MID-RECON (EOD datastore) | C24: Cache | D24: Infrastructure | E24: Recon/pipeline | F24: DTR | G24: Fail Redis while DTR is mid-reconciliation (EOD txn cache in use). | H24: Recon detects datastore loss, fails safe (no partial/incorrect postings), and is restartable — re-pull from CBS EOD API rather than corrupt continuation. | I24: FIS/console failover + custom timing | J24: Recon run | K24: ANY posting correction from bad state | L24: No incorrect Posting-API corrections; rerun completes in window; Redis-as-datastore (not cache) risk documented. | M24: Mid-run datastore loss pages recon on-call immediately. | N24: High | O24: Logic-level; file volumes smaller in PERF (timing caveat). | P24: 2 | Q24: 5 | R24: =P24*Q24 | S24: 2 | T24: CE-CACHE-01,CE-PIPE-10 | W24: Proposed | X24: =IF(P24=5,"Almost Certain",IF(P24=4,"Likely",IF(P24=3,"Possible",IF(P24=2,"Unlikely","Rare")))) | Y24: =IF(R24>=16,"Critical",IF(R24>=9,"High",IF(R24>=4,"Medium","Opportunistic")))
A25: CE-CACHE-06 | B25: Recon purge failure — memory accumulation | C25: Cache | D25: Detection | E25: Recon/pipeline | F25: DTR | G25: Suppress the post-recon purge (step 10) across simulated cycles. | H25: Memory-pressure trend is detected well before eviction threatens the next recon's EOD dataset. | I25: Custom (skip purge in PERF) | J25: Redis capacity trend | K25: n/a (observation) | L25: Days-to-failure runway quantified. | M25: Trend alarm exists with adequate lead time (suspected gap). | N25: High | O25: Trend math transfers. | P25: 2 | Q25: 4 | R25: =P25*Q25 | S25: 2 | W25: Proposed | X25: =IF(P25=5,"Almost Certain",IF(P25=4,"Likely",IF(P25=3,"Possible",IF(P25=2,"Unlikely","Rare")))) | Y25: =IF(R25>=16,"Critical",IF(R25>=9,"High",IF(R25>=4,"Medium","Opportunistic")))
A26: CE-CACHE-07 | B26: Post-regional-failover cold cache | C26: Cache | D26: Infrastructure | E26: All cache users | F26: Surviving-region Redis | G26: Per-region static clusters ⇒ regional failover lands on a cold cache. Simulate by directing load at standby-region cache. | H26: Surviving region absorbs cold-start read amplification during DR without breaching Aurora capacity. | I26: Custom + load | J26: Standby region | K26: Aurora saturation | L26: Cold-start curve measured; feeds DR capacity plan and CE-CMP-05. | M26: Standby-region dashboards actually populated (validate). | N26: Medium | O26: Standby capacity parity TBD. | P26: 3 | Q26: 4 | R26: =P26*Q26 | S26: 3 | T26: CE-CACHE-04 | W26: Proposed | X26: =IF(P26=5,"Almost Certain",IF(P26=4,"Likely",IF(P26=3,"Possible",IF(P26=2,"Unlikely","Rare")))) | Y26: =IF(R26>=16,"Critical",IF(R26>=9,"High",IF(R26>=4,"Medium","Opportunistic")))
A27: CE-KFK-01 | B27: MBUS cluster unreachable | C27: Messaging-Kafka | D27: Infrastructure | E27: Event processor + publishers | F27: DBE, DTE, DSC, DAL, DSM, SAM, DCM, AFM | G27: Blackhole network path to on-prem MBUS (C001/C002). | H27: Consumers idle without crash-loop; producers buffer/queue per config without data loss or unbounded memory; full catch-up on restore with no gaps/dupes. | I27: Custom (network blackhole PERF) | J27: All Kafka traffic | K27: Producer memory growth unbounded | L27: Zero event loss post-restore; backlog drain time measured; producer overflow policy proven. | M27: Broker-unreachable alarm + per-consumer lag visible. | N27: High | O27: Client behavior transfers; on-prem path is same class of fault as PROD DX loss. | P27: 3 | Q27: 5 | R27: =P27*Q27 | S27: 2 | T27: CE-KFK-06 | W27: Proposed | X27: =IF(P27=5,"Almost Certain",IF(P27=4,"Likely",IF(P27=3,"Possible",IF(P27=2,"Unlikely","Rare")))) | Y27: =IF(R27>=16,"Critical",IF(R27>=9,"High",IF(R27>=4,"Medium","Opportunistic")))
A28: CE-KFK-02 | B28: MBUS unreachable during EOD window | C28: Messaging-Kafka | D28: Compound | E28: Recon + processors | F28: DTR primarily | G28: MBUS outage timed across CBS EOD Completion publication. | H28: DTR's missing-trigger handling (see PIPE-06) engages; recon completes late-but-correct via defined recovery, inside business tolerance. | I28: Custom timing | J28: EOD processing | K28: Recon SLA breach unmanaged | L28: Recovery path exercised end-to-end; late-recon comms path (EDX/Ops) fires. | M28: EOD-event-absence alarm with deadline semantics (suspected gap). | N28: High | O28: — | P28: 2 | Q28: 5 | R28: =P28*Q28 | S28: 3 | T28: CE-KFK-01,CE-PIPE-06 | W28: Proposed | X28: =IF(P28=5,"Almost Certain",IF(P28=4,"Likely",IF(P28=3,"Possible",IF(P28=2,"Unlikely","Rare")))) | Y28: =IF(R28>=16,"Critical",IF(R28>=9,"High",IF(R28>=4,"Medium","Opportunistic")))
A29: CE-KFK-03 | B29: Consumer rebalance storm | C29: Messaging-Kafka | D29: Infrastructure | E29: Event processor | F29: DBE or DTE | G29: Repeatedly kill/restart consumer tasks to force serial rebalances. | H29: Rebalance protocol (cooperative?) limits pause; no duplicate enrichment side-effects; lag recovers between storms. | I29: FIS stop-task loop | J29: One consumer group | K29: Duplicate enriched events downstream | L29: Processing-pause per rebalance quantified; assignment strategy validated. | M29: Rebalance frequency alarmed as abnormal. | N29: High | O29: — | P29: 3 | Q29: 3 | R29: =P29*Q29 | S29: 2 | T29: CE-COM-04 | W29: Proposed | X29: =IF(P29=5,"Almost Certain",IF(P29=4,"Likely",IF(P29=3,"Possible",IF(P29=2,"Unlikely","Rare")))) | Y29: =IF(R29>=16,"Critical",IF(R29>=9,"High",IF(R29>=4,"Medium","Opportunistic")))
A30: CE-KFK-04 | B30: Poison message handling | C30: Messaging-Kafka | D30: Application | E30: Event processor | F30: DBE, DTE, DSC, DAL (each) | G30: Publish malformed/contract-violating event to PERF topic. | H30: Consumer parks/DLQs the message and CONTINUES — one bad event cannot halt the partition (classic head-of-line risk). | I30: Custom producer (PERF topics) | J30: One partition | K30: Partition stalled >5 min | L30: Skip/park behavior proven per consumer; replay procedure exists. | M30: Poison/parked-message alarm fires with payload pointer. | N30: High | O30: Logic-level. | P30: 4 | Q30: 4 | R30: =P30*Q30 | S30: 1 | W30: Proposed | X30: =IF(P30=5,"Almost Certain",IF(P30=4,"Likely",IF(P30=3,"Possible",IF(P30=2,"Unlikely","Rare")))) | Y30: =IF(R30>=16,"Critical",IF(R30>=9,"High",IF(R30>=4,"Medium","Opportunistic")))
A31: CE-KFK-05 | B31: Duplicate delivery idempotency | C31: Messaging-Kafka | D31: Application | E31: Event processor | F31: DBE, DTE, DSC, DAL (each) | G31: Re-publish already-processed events (at-least-once reality). | H31: Every consumer is effectively idempotent: no duplicate enriched events to AU/ETU, no duplicate alerts to NOTIFY, no double cache writes. | I31: Custom producer | J31: Downstream consumers | K31: Any duplicate side-effect | L31: Idempotency proven per consumer per event type. | M31: Duplicate-detection metrics exist (nice-to-have). | N31: High | O31: Logic-level. | P31: 4 | Q31: 4 | R31: =P31*Q31 | S31: 1 | W31: Proposed | X31: =IF(P31=5,"Almost Certain",IF(P31=4,"Likely",IF(P31=3,"Possible",IF(P31=2,"Unlikely","Rare")))) | Y31: =IF(R31>=16,"Critical",IF(R31>=9,"High",IF(R31>=4,"Medium","Opportunistic")))
A32: CE-KFK-06 | B32: Consumer lag accumulation & drain | C32: Messaging-Kafka | D32: Infrastructure | E32: Event processor | F32: DBE, DTE | G32: Pause consumption (scale to 0) for a bounded window, then resume. | H32: Backlog drains within recovery-time model; ordering preserved; downstream (AU/ETU) absorbs burst. | I32: Scale-to-zero + resume | J32: One consumer group | K32: Retention risk approached | L32: Drain rate measured ⇒ max tolerable outage derived (feeds KFK-01/02). | M32: Lag alarm thresholds validated against real drain math. | N32: Medium | O32: Throughput differs in PERF; drain RATE transfers, absolute times don't. | P32: 3 | Q32: 3 | R32: =P32*Q32 | S32: 1 | W32: Proposed | X32: =IF(P32=5,"Almost Certain",IF(P32=4,"Likely",IF(P32=3,"Possible",IF(P32=2,"Unlikely","Rare")))) | Y32: =IF(R32>=16,"Critical",IF(R32>=9,"High",IF(R32>=4,"Medium","Opportunistic")))
A33: CE-KFK-07 | B33: IDP OAUTHBEARER token failure (Kafka auth) | C33: Messaging-Kafka | D33: Infrastructure | E33: All Kafka clients | F33: One consumer + one producer | G33: Block IDP token issuance for Kafka SASL auth; include re-auth boundary. | H33: Existing sessions survive to re-auth boundary; failed re-auth backs off sanely (no auth-storm against IDP); clear failure signature. | I33: Custom (IDP path block PERF) | J33: Kafka connectivity | K33: Auth retry storm | L33: Session lifetime + backoff behavior documented; recovery clean. | M33: Kafka-auth failure distinct from broker-unreachable in alerts. | N33: High | O33: — | P33: 2 | Q33: 4 | R33: =P33*Q33 | S33: 2 | W33: Proposed | X33: =IF(P33=5,"Almost Certain",IF(P33=4,"Likely",IF(P33=3,"Possible",IF(P33=2,"Unlikely","Rare")))) | Y33: =IF(R33>=16,"Critical",IF(R33>=9,"High",IF(R33>=4,"Medium","Opportunistic")))
A34: CE-KFK-08 | B34: KMS key access denial — encrypted topics | C34: Messaging-Kafka | D34: Infrastructure | E34: Publisher/consumer | F34: DSM, DBE (subledger/balance event aliases) | G34: Deny kms:Decrypt/Encrypt on topic keys for the service role. | H34: Publish/consume fails closed with explicit KMS error; no silent drop; processing halts visibly and resumes on restore. | I34: Custom (KMS key policy PERF) | J34: Encrypted event flows | K34: Silent event loss | L34: Zero loss; halt-and-resume clean. | M34: KMS-denial signature alarmed. | N34: High | O34: — | P34: 2 | Q34: 4 | R34: =P34*Q34 | S34: 2 | W34: Proposed | X34: =IF(P34=5,"Almost Certain",IF(P34=4,"Likely",IF(P34=3,"Possible",IF(P34=2,"Unlikely","Rare")))) | Y34: =IF(R34>=16,"Critical",IF(R34>=9,"High",IF(R34>=4,"Medium","Opportunistic")))
A35: CE-KFK-09 | B35: PLACEHOLDER — Kafka SaaS migration scenario set | C35: Messaging-Kafka | D35: TBD | E35: Event processor | F35: TBD | G35: Reserved: re-run KFK-01..08 against Kafka SaaS on AWS; add SaaS-specific faults (quota throttling, private-link path, provider AZ events). | H35: TBD when platform selected. | I35: TBD | J35: TBD | K35: TBD | L35: TBD | M35: TBD | N35: TBD | O35: Per user direction: placeholder only, do not plan yet. | P35: 0 | Q35: 0 | R35: =P35*Q35 | S35: 4 | T35: CE-KFK-01 | W35: Proposed | X35: =IF(P35=5,"Almost Certain",IF(P35=4,"Likely",IF(P35=3,"Possible",IF(P35=2,"Unlikely","Rare")))) | Y35: =IF(R35>=16,"Critical",IF(R35>=9,"High",IF(R35>=4,"Medium","Opportunistic")))
A36: CE-PIPE-01 | B36: Input file late/missing at cutoff | C36: Pipeline-Recon | D36: Application | E36: Recon/pipeline | F36: DTR + EDX path | G36: Withhold RDF/ADF/CDF file for one bank past cutoff. | H36: EventBridge SLA validator detects absence at cutoff and EDX email notification fires (narrative step 2a); recon for other banks proceeds unaffected. | I36: Custom (withhold in PERF) | J36: One bank's recon | K36: Cross-bank impact | L36: Per-bank isolation proven; notification content actionable. | M36: SLA-validator alarm + email verified end-to-end. | N36: High | O36: Same mechanism as PROD. | P36: 4 | Q36: 4 | R36: =P36*Q36 | S36: 1 | W36: Proposed | X36: =IF(P36=5,"Almost Certain",IF(P36=4,"Likely",IF(P36=3,"Possible",IF(P36=2,"Unlikely","Rare")))) | Y36: =IF(R36>=16,"Critical",IF(R36>=9,"High",IF(R36>=4,"Medium","Opportunistic")))
A37: CE-PIPE-02 | B37: Corrupt / malformed input file | C37: Pipeline-Recon | D37: Application | E37: Recon/pipeline | F37: DTR (Lambda validate/parse) | G37: Deliver structurally invalid and semantically invalid files. | H37: Validation Lambda rejects cleanly; rejection reaches Ops/EDX; no partial ingestion poisons downstream SQS. | I37: Custom file injection | J37: One file's flow | K37: Partial ingestion detected | L37: Reject path + quarantine proven; reprocess-after-fix works. | M37: Rejection alarmed with file identity. | N37: High | O37: — | P37: 4 | Q37: 4 | R37: =P37*Q37 | S37: 1 | W37: Proposed | X37: =IF(P37=5,"Almost Certain",IF(P37=4,"Likely",IF(P37=3,"Possible",IF(P37=2,"Unlikely","Rare")))) | Y37: =IF(R37>=16,"Critical",IF(R37>=9,"High",IF(R37>=4,"Medium","Opportunistic")))
A38: CE-PIPE-03 | B38: Duplicate file delivery | C38: Pipeline-Recon | D38: Application | E38: Recon/pipeline | F38: DTR | G38: Deliver the same file twice (and same-name-different-content variant). | H38: Ingestion is idempotent by file identity; no duplicate transaction records enter reconciliation; conflict variant is flagged, not silently overwritten. | I38: Custom file injection | J38: One bank's recon | K38: Duplicate records in recon set | L38: Dedup keys proven; conflict handling explicit. | M38: Duplicate-delivery event logged/alarmed. | N38: High | O38: — | P38: 3 | Q38: 4 | R38: =P38*Q38 | S38: 1 | W38: Proposed | X38: =IF(P38=5,"Almost Certain",IF(P38=4,"Likely",IF(P38=3,"Possible",IF(P38=2,"Unlikely","Rare")))) | Y38: =IF(R38>=16,"Critical",IF(R38>=9,"High",IF(R38>=4,"Medium","Opportunistic")))
A39: CE-PIPE-04 | B39: Lambda throttling on large-file day | C39: Pipeline-Recon | D39: Infrastructure | E39: Recon/pipeline | F39: DTR chunking Lambda | G39: Lower reserved concurrency in PERF + inject peak-size file set. | H39: Throttled invocations retry via SQS without loss or duplication of chunks; end-to-end completes within window at degraded rate. | I39: Custom (concurrency limit) | J39: Chunking stage | K39: Chunk loss or duplication | L39: Exactly-once chunk effects; window math validated for peak day. | M39: Throttle + queue-age alarms fire before SLA risk. | N39: Medium | O39: PERF file volumes smaller — use synthetic peak set. | P39: 3 | Q39: 4 | R39: =P39*Q39 | S39: 2 | W39: Proposed | X39: =IF(P39=5,"Almost Certain",IF(P39=4,"Likely",IF(P39=3,"Possible",IF(P39=2,"Unlikely","Rare")))) | Y39: =IF(R39>=16,"Critical",IF(R39>=9,"High",IF(R39>=4,"Medium","Opportunistic")))
A40: CE-PIPE-05 | B40: SQS DLQ + redrive validation | C40: Pipeline-Recon | D40: Infrastructure | E40: Recon/pipeline | F40: DTR queues (+ DCM weekly-job queue) | G40: Force message processing failures to exhaust receive count. | H40: Messages land in DLQ (not lost, not infinitely retried); redrive procedure restores processing without duplication. | I40: Custom (failure injection) | J40: One queue | K40: Message loss | L40: maxReceiveCount/visibility tuned; redrive runbook proven. | M40: DLQ depth alarm fires at first message. | N40: High | O40: — | P40: 3 | Q40: 4 | R40: =P40*Q40 | S40: 1 | W40: Proposed | X40: =IF(P40=5,"Almost Certain",IF(P40=4,"Likely",IF(P40=3,"Possible",IF(P40=2,"Unlikely","Rare")))) | Y40: =IF(R40>=16,"Critical",IF(R40>=9,"High",IF(R40>=4,"Medium","Opportunistic")))
A41: CE-PIPE-06 | B41: Dual-trigger failure A: files present, CBS EOD event absent | C41: Pipeline-Recon | D41: Application | E41: Recon/pipeline | F41: DTR | G41: Deliver files normally; suppress CBS EOD Completion event. | H41: Recon does NOT start on partial trigger; absence is detected against a deadline; defined recovery (manual trigger / EOD API poll) exists and works. | I41: Custom (event suppression PERF) | J41: EOD recon | K41: Recon starts on partial data | L41: No premature recon; deadline detection + recovery path proven. | M41: EOD-event-absence alarm with time semantics (suspected gap — narrative silent on this). | N41: High | O41: Design-gap probe — likely FINDING. | P41: 3 | Q41: 5 | R41: =P41*Q41 | S41: 1 | W41: Proposed | X41: =IF(P41=5,"Almost Certain",IF(P41=4,"Likely",IF(P41=3,"Possible",IF(P41=2,"Unlikely","Rare")))) | Y41: =IF(R41>=16,"Critical",IF(R41>=9,"High",IF(R41>=4,"Medium","Opportunistic")))
A42: CE-PIPE-07 | B42: Dual-trigger failure B: EOD event present, files absent | C42: Pipeline-Recon | D42: Application | E42: Recon/pipeline | F42: DTR | G42: Publish EOD event; withhold files. | H42: Recon waits for file leg per step-4a note; combined absence handling matches PIPE-01 path; no empty-set recon marked successful. | I42: Custom | J42: EOD recon | K42: Recon 'succeeds' on empty set | L42: No false recon-success; Acct Closure event (step 9) NOT published for unreconciled day. | M42: False-success guard alarmed. | N42: High | O42: — | P42: 3 | Q42: 5 | R42: =P42*Q42 | S42: 1 | T42: CE-PIPE-01 | W42: Proposed | X42: =IF(P42=5,"Almost Certain",IF(P42=4,"Likely",IF(P42=3,"Possible",IF(P42=2,"Unlikely","Rare")))) | Y42: =IF(R42>=16,"Critical",IF(R42>=9,"High",IF(R42>=4,"Medium","Opportunistic")))
A43: CE-PIPE-08 | B43: SLA-validator scheduler misfire / double-fire | C43: Pipeline-Recon | D43: Infrastructure | E43: Recon/pipeline | F43: DTR EventBridge | G43: Disable rule for one window; separately duplicate-trigger it. | H43: Missed validation window is itself detected (who watches the watcher); double-fire causes no duplicate notifications/side-effects. | I43: Custom (rule manipulation PERF) | J43: SLA validation | K43: n/a | L43: Validator idempotent; meta-monitoring exists or gap logged. | M43: Scheduler failure visibility (suspected gap). | N43: High | O43: — | P43: 2 | Q43: 4 | R43: =P43*Q43 | S43: 2 | W43: Proposed | X43: =IF(P43=5,"Almost Certain",IF(P43=4,"Likely",IF(P43=3,"Possible",IF(P43=2,"Unlikely","Rare")))) | Y43: =IF(R43>=16,"Critical",IF(R43>=9,"High",IF(R43>=4,"Medium","Opportunistic")))
A44: CE-PIPE-09 | B44: S3 recon-bucket unavailability / latency | C44: Pipeline-Recon | D44: Infrastructure | E44: Recon/pipeline | F44: DTR buckets | G44: Deny bucket access mid-pipeline (PERF bucket policy). | H44: Each stage fails visibly and resumes idempotently on restore; ack/anomaly file writes are not silently skipped. | I44: Custom (bucket policy) | J44: Recon storage | K44: Silent skip of outputs | L44: Stage-level retry/resume proven. | M44: S3 access errors alarmed per stage. | N44: High | O44: — | P44: 2 | Q44: 4 | R44: =P44*Q44 | S44: 2 | W44: Proposed | X44: =IF(P44=5,"Almost Certain",IF(P44=4,"Likely",IF(P44=3,"Possible",IF(P44=2,"Unlikely","Rare")))) | Y44: =IF(R44>=16,"Critical",IF(R44>=9,"High",IF(R44>=4,"Medium","Opportunistic")))
A45: CE-PIPE-10 | B45: Recon abort mid-run → restart idempotency | C45: Pipeline-Recon | D45: Application | E45: Recon/pipeline | F45: DTR | G45: Kill recon service at defined checkpoints incl. AFTER some Posting-API corrections have been sent. | H45: Restart produces exactly-once EFFECTS: no duplicate posting corrections, no re-sent Acct-Closure/Recon events, resumable from checkpoint. | I45: FIS stop-task + checkpoint timing | J45: Recon run + CBS postings | K45: Any duplicate posting correction | L45: Exactly-once effects proven at every checkpoint — the single highest-integrity-risk scenario in the catalog. | M45: Partial-run state visible to Ops. | N45: High | O45: Logic-level; PERF CBS dedicated instance receives corrections — confirm reversibility. | P45: 3 | Q45: 5 | R45: =P45*Q45 | S45: 1 | W45: Proposed | X45: =IF(P45=5,"Almost Certain",IF(P45=4,"Likely",IF(P45=3,"Possible",IF(P45=2,"Unlikely","Rare")))) | Y45: =IF(R45>=16,"Critical",IF(R45>=9,"High",IF(R45>=4,"Medium","Opportunistic")))
A46: CE-PIPE-11 | B46: Forced cutoff-mismatch → TransactionInquiry SOR fallback | C46: Pipeline-Recon | D46: Application | E46: Recon/pipeline | F46: DTR + Core Transaction Svc | G46: Engineer EOD dataset gaps so lookups miss (LCDP/CBS cutoff skew per narrative 5a). | H46: Fallback to Core TransactionInquiry engages per design; result parity with primary path; fallback latency doesn't blow the window. | I46: Custom dataset manipulation | J46: Recon matching | K46: Mismatch mis-posted | L46: Fallback correctness + performance measured. | M46: Fallback-rate metric exists (leading indicator of cutoff drift). | N46: High | O46: — | P46: 3 | Q46: 4 | R46: =P46*Q46 | S46: 2 | T46: CE-PIPE-10 | W46: Proposed | X46: =IF(P46=5,"Almost Certain",IF(P46=4,"Likely",IF(P46=3,"Possible",IF(P46=2,"Unlikely","Rare")))) | Y46: =IF(R46>=16,"Critical",IF(R46>=9,"High",IF(R46>=4,"Medium","Opportunistic")))
A47: CE-NET-01 | B47: Inter-service latency / packet-loss injection | C47: Network | D47: Infrastructure | E47: Sync API | F47: Service pairs on critical path | G47: FIS network latency/loss actions on Fargate tasks (requires fault-injection endpoints + pidMode:task — availability TBC, Open Items). | H47: Latency propagates per timeout chain, not as hangs; loss triggers retries within budget without amplification. | I47: FIS network actions (TBC) / fallback tc-sidecar | J47: Selected pairs | K47: SLI breach | L47: Degradation graceful and bounded. | M47: Latency SLIs per hop visible in Dynatrace. | N47: High | O47: — | P47: 3 | Q47: 4 | R47: =P47*Q47 | S47: 2 | T47: CE-EDGE-01 | W47: Proposed | X47: =IF(P47=5,"Almost Certain",IF(P47=4,"Likely",IF(P47=3,"Possible",IF(P47=2,"Unlikely","Rare")))) | Y47: =IF(R47>=16,"Critical",IF(R47>=9,"High",IF(R47>=4,"Medium","Opportunistic")))
A48: CE-NET-02 | B48: AZ impairment | C48: Network | D48: Infrastructure | E48: All in-region | F48: One AZ's subnets | G48: Blackhole one AZ (FIS network blackhole / NACL). | H48: Multi-AZ placement absorbs loss: ALB routes around, ECS reschedules, Aurora AZ redundancy holds; capacity floor per service ≥ requirement at N-1 AZ. | I48: FIS / custom NACL | J48: One AZ | K48: Any single-AZ SPOF found | L48: No service loses quorum/capacity below SLO; SPOFs enumerated if found. | M48: AZ-level health visible; alarms not double-firing per task. | N48: Medium | O48: PERF AZ spread/capacity parity TBD. | P48: 2 | Q48: 5 | R48: =P48*Q48 | S48: 2 | T48: CE-COM-02 | W48: Proposed | X48: =IF(P48=5,"Almost Certain",IF(P48=4,"Likely",IF(P48=3,"Possible",IF(P48=2,"Unlikely","Rare")))) | Y48: =IF(R48>=16,"Critical",IF(R48>=9,"High",IF(R48>=4,"Medium","Opportunistic")))
A49: CE-NET-03 | B49: On-prem path loss (DX) — MBUS / GKP / on-prem API GW | C49: Network | D49: Infrastructure | E49: Cross-cutting | F49: MBUS clients, TE (GKP via Envoy), MCC (on-prem API GW) | G49: Blackhole on-prem-bound routes. | H49: Each on-prem dependency fails per its class: Kafka per KFK-01; TE's GKP calls fail fast with degraded UX; MCC serves from local store/S3 config without on-prem GW. | I49: Custom (route blackhole PERF) | J49: All on-prem traffic | K49: TE hard-down | L49: Blast radius of DX loss fully mapped — key DR planning input. | M49: DX-path health alarmed as a NAMED failure domain (suspected gap). | N49: High | O49: Same failure class as PROD DX loss. | P49: 2 | Q49: 5 | R49: =P49*Q49 | S49: 2 | T49: CE-KFK-01 | W49: Proposed | X49: =IF(P49=5,"Almost Certain",IF(P49=4,"Likely",IF(P49=3,"Possible",IF(P49=2,"Unlikely","Rare")))) | Y49: =IF(R49>=16,"Critical",IF(R49>=9,"High",IF(R49>=4,"Medium","Opportunistic")))
A50: CE-NET-04 | B50: VPC endpoint (PrivateLink) failure | C50: Network | D50: Infrastructure | E50: All | F50: AWS service endpoints (TBC applicability) | G50: Remove/deny a VPC endpoint used for AWS service access. | H50: SDK calls fail visibly (no long hangs); dependency on each endpoint enumerated. | I50: Custom (endpoint policy) | J50: Per endpoint | K50: Hangs beyond timeout | L50: Endpoint dependency map produced. | M50: Endpoint failures distinguishable in telemetry. | N50: High | O50: Confirm endpoint architecture first (Open Items). | P50: 2 | Q50: 3 | R50: =P50*Q50 | S50: 3 | W50: Proposed | X50: =IF(P50=5,"Almost Certain",IF(P50=4,"Likely",IF(P50=3,"Possible",IF(P50=2,"Unlikely","Rare")))) | Y50: =IF(R50>=16,"Critical",IF(R50>=9,"High",IF(R50>=4,"Medium","Opportunistic")))
A51: CE-EDGE-01 | B51: Timeout chain ordering validation | C51: Edge | D51: Application | E51: Sync API | F51: One representative service per APG | G51: Inject stepped latency BETWEEN each configured threshold: just above HikariCP, just below Feign/R4j, ALB idle, NLB idle (350s), API GW (29s). | H51: Timeouts fire in the documented order from the timeout-alignment work; every layer's failure is attributable; no silent NLB drops or API-GW-first surprises. | I51: App-level latency (Chaos Monkey for Spring Boot) + Toxiproxy | J51: One call path | K51: n/a (measurement) | L51: Empirical firing order == documented order, per path. Deviations are FMEA findings. | M51: Each layer's timeout distinguishable in traces. | N51: High | O51: Config-level; verify PERF configs == PROD (Open Items). | P51: 4 | Q51: 4 | R51: =P51*Q51 | S51: 1 | W51: Proposed | X51: =IF(P51=5,"Almost Certain",IF(P51=4,"Likely",IF(P51=3,"Possible",IF(P51=2,"Unlikely","Rare")))) | Y51: =IF(R51>=16,"Critical",IF(R51>=9,"High",IF(R51>=4,"Medium","Opportunistic")))
A52: CE-EDGE-02 | B52: NLB idle-timeout behavior (350s silent drop) | C52: Edge | D52: Application | E52: Sync API | F52: Long-call paths; DSM external→internal NLB pair | G52: Hold connections idle past 350s; observe RST-on-next-byte semantics through the double-NLB DSM path. | H52: No legitimate call path approaches NLB idle limits; keepalive settings prevent surprise resets on reused connections. | I52: Custom client | J52: Selected paths | K52: n/a | L52: Keepalive < NLB idle proven per hop. | M52: Connection-reset anomalies visible. | N52: High | O52: — | P52: 2 | Q52: 3 | R52: =P52*Q52 | S52: 2 | T52: CE-EDGE-01 | W52: Proposed | X52: =IF(P52=5,"Almost Certain",IF(P52=4,"Likely",IF(P52=3,"Possible",IF(P52=2,"Unlikely","Rare")))) | Y52: =IF(R52>=16,"Critical",IF(R52>=9,"High",IF(R52>=4,"Medium","Opportunistic")))
A53: CE-EDGE-03 | B53: API Gateway throttle breach | C53: Edge | D53: Infrastructure | E53: Sync API | F53: One API per APG | G53: Drive load past configured rate/burst limits. | H53: 429s returned cleanly; callers back off (no retry hammering); throttle limits match capacity math. | I53: Load generator | J53: One API | K53: Retry amplification | L53: Backoff-on-429 proven caller-side. | M53: Throttle events alarmed with caller attribution. | N53: High | O53: Limits config parity TBC. | P53: 3 | Q53: 3 | R53: =P53*Q53 | S53: 2 | W53: Proposed | X53: =IF(P53=5,"Almost Certain",IF(P53=4,"Likely",IF(P53=3,"Possible",IF(P53=2,"Unlikely","Rare")))) | Y53: =IF(R53>=16,"Critical",IF(R53>=9,"High",IF(R53>=4,"Medium","Opportunistic")))
A54: CE-EDGE-04 | B54: ALB drain during deploy under load | C54: Edge | D54: Infrastructure | E54: Sync API | F54: One service | G54: Deploy under load; measure deregistration-delay vs in-flight request duration. | H54: Zero in-flight kills: drain timeout ≥ p99 request duration; connection reuse doesn't route to draining targets. | I54: Deploy + load | J54: One service | K54: 5xx during drain | L54: Drain settings validated against real p99. | M54: Deploy-window error attribution clean. | N54: High | O54: — | P54: 3 | Q54: 3 | R54: =P54*Q54 | S54: 2 | T54: CE-COM-03 | W54: Proposed | X54: =IF(P54=5,"Almost Certain",IF(P54=4,"Likely",IF(P54=3,"Possible",IF(P54=2,"Unlikely","Rare")))) | Y54: =IF(R54>=16,"Critical",IF(R54>=9,"High",IF(R54>=4,"Medium","Opportunistic")))
A55: CE-EDGE-05 | B55: DPS Proxy path degradation (3-active edges) | C55: Edge | D55: Infrastructure | E55: Edge/BFF | F55: TE, CHE, SSE | G55: Degrade one region's DPS-Proxy-fronted path (latency/errors upstream of R53). | H55: 3-active routing shifts traffic away from impaired region; stateless services show no session breakage; user-visible impact bounded. | I55: Custom (upstream injection) / coordination | J55: One region's edge | K55: User-visible errors sustained | L55: Traffic-shift behavior measured incl. shift-back. | M55: Regional edge health per region visible. | N55: Low | O55: us-west-2 presence + DPS Proxy parity in PERF TBC (Open Items). | P55: 2 | Q55: 4 | R55: =P55*Q55 | S55: 3 | W55: Proposed | X55: =IF(P55=5,"Almost Certain",IF(P55=4,"Likely",IF(P55=3,"Possible",IF(P55=2,"Unlikely","Rare")))) | Y55: =IF(R55>=16,"Critical",IF(R55>=9,"High",IF(R55>=4,"Medium","Opportunistic")))
A56: CE-EDGE-06 | B56: DLAT direct path (no API GW) exposure check | C56: Edge | D56: Application | E56: Admin tool | F56: DLAT | G56: Exercise DLAT's R53→NLB→ALB path under fault (latency, auth anomalies). | H56: Protections absent from skipping API GW (throttle, auth at edge) are compensated elsewhere — or documented as accepted risk. | I56: Custom | J56: DLAT | K56: n/a | L56: Control gap analysis complete (feeds DLAT documentation gap). | M56: DLAT traffic observable at all (suspected gap). | N56: High | O56: — | P56: 2 | Q56: 3 | R56: =P56*Q56 | S56: 3 | W56: Proposed | X56: =IF(P56=5,"Almost Certain",IF(P56=4,"Likely",IF(P56=3,"Possible",IF(P56=2,"Unlikely","Rare")))) | Y56: =IF(R56>=16,"Critical",IF(R56>=9,"High",IF(R56>=4,"Medium","Opportunistic")))
A57: CE-EXT-01 | B57: CBS Posting 5xx burst | C57: External Dep | D57: Application | E57: Sync API / Recon | F57: AFM, DCM, DTR corrections | G57: Inject 5xx from CBS Posting via proxy layer in front of dedicated PERF CBS instance. | H57: R4j breaker on the Posting client trips on failure-rate; callers queue/park work per design; no lost postings — retried or parked, never dropped. | I57: Toxiproxy/injection proxy (PERF CBS is live — cannot be failed itself) | J57: Posting-dependent flows | K57: Posting silently dropped | L57: Breaker + park/retry semantics proven; recovery drains parked work. | M57: CBS-Posting health as seen FROM Core alarmed (not just CBS's own monitoring). | N57: High | O57: Dedicated PERF CBS: inject in front, never break the instance. | P57: 3 | Q57: 5 | R57: =P57*Q57 | S57: 1 | W57: Proposed | X57: =IF(P57=5,"Almost Certain",IF(P57=4,"Likely",IF(P57=3,"Possible",IF(P57=2,"Unlikely","Rare")))) | Y57: =IF(R57>=16,"Critical",IF(R57>=9,"High",IF(R57>=4,"Medium","Opportunistic")))
A58: CE-EXT-02 | B58: CBS slow-but-alive (gray failure) | C58: External Dep | D58: Application | E58: Sync API | F58: AFM, DSM, DCM (CBS callers) | G58: Inject 5–15s latency (no errors) on CBS responses. | H58: SLOW-CALL-RATE breaker path trips (distinct code path from failure-rate); threads don't pool-exhaust waiting; timeout chain caps caller exposure. | I58: Toxiproxy latency | J58: CBS callers | K58: Thread pool exhaustion | L58: Slow-call breaker config proven per service — the highest-value app-level test in the catalog. | M58: Latency-based alerting fires BEFORE error-based. | N58: High | O58: — | P58: 4 | Q58: 5 | R58: =P58*Q58 | S58: 1 | T58: CE-EDGE-01 | W58: Proposed | X58: =IF(P58=5,"Almost Certain",IF(P58=4,"Likely",IF(P58=3,"Possible",IF(P58=2,"Unlikely","Rare")))) | Y58: =IF(R58>=16,"Critical",IF(R58>=9,"High",IF(R58>=4,"Medium","Opportunistic")))
A59: CE-EXT-03 | B59: CBS event stream stall | C59: External Dep | D59: Application | E59: Event processor | F59: DBE, DTE | G59: Suppress CBS Balance/Transaction events (consumers healthy, topic silent). | H59: Silence is DETECTED as anomaly (expected-throughput heartbeat), not just absence of errors — classic silent-failure trap. | I59: Custom (suppress at source/proxy) | J59: Enrichment freshness | K59: n/a (detection) | L59: Staleness of enriched data downstream (AU/ETU) bounded + alarmed. | M59: Throughput-floor / heartbeat alarm exists (suspected gap). | N59: High | O59: — | P59: 3 | Q59: 4 | R59: =P59*Q59 | S59: 1 | W59: Proposed | X59: =IF(P59=5,"Almost Certain",IF(P59=4,"Likely",IF(P59=3,"Possible",IF(P59=2,"Unlikely","Rare")))) | Y59: =IF(R59>=16,"Critical",IF(R59>=9,"High",IF(R59>=4,"Medium","Opportunistic")))
A60: CE-EXT-04 | B60: LCDP degradation | C60: External Dep | D60: Application | E60: Per dependency map | F60: LCDP callers | G60: Inject errors/latency on LCDP calls. | H60: Callers degrade per design (fallback/cached/deferred) without journey hard-failure where FMEA says soft-fail. | I60: Toxiproxy | J60: LCDP callers | K60: Hard failure where soft expected | L60: Documented degradation mode matches reality. | M60: LCDP-as-seen-from-Core health visible. | N60: High | O60: — | P60: 3 | Q60: 4 | R60: =P60*Q60 | S60: 2 | W60: Proposed | X60: =IF(P60=5,"Almost Certain",IF(P60=4,"Likely",IF(P60=3,"Possible",IF(P60=2,"Unlikely","Rare")))) | Y60: =IF(R60>=16,"Critical",IF(R60>=9,"High",IF(R60>=4,"Medium","Opportunistic")))
A61: CE-EXT-05 | B61: AU / ETU unavailable (enriched-event downstream) | C61: External Dep | D61: Application | E61: Event processor | F61: DBE→AU, DTE→ETU paths | G61: Block delivery of enriched events to AU/ETU (Kafka-side or consumer-side per topology). | H61: Enriched events are durable in MBUS regardless of downstream health (pub/sub decoupling holds); no producer-side blocking. | I61: Custom | J61: Enrichment egress | K61: Producer blocked by consumer health | L61: Decoupling proven; downstream catch-up clean. | M61: Downstream-lag-on-our-topics visibility (whose alarm? — governance note). | N61: High | O61: — | P61: 2 | Q61: 3 | R61: =P61*Q61 | S61: 2 | W61: Proposed | X61: =IF(P61=5,"Almost Certain",IF(P61=4,"Likely",IF(P61=3,"Possible",IF(P61=2,"Unlikely","Rare")))) | Y61: =IF(R61>=16,"Critical",IF(R61>=9,"High",IF(R61>=4,"Medium","Opportunistic")))
A62: CE-EXT-06 | B62: CSU failure — alert enrichment | C62: External Dep | D62: Application | E62: Event processor | F62: DAL | G62: Fail CSU (parent/child fetch) during alert processing. | H62: DAL degrades per design: alert sent without enrichment OR parked for cron recovery (its documented failure-recovery scheduler) — never silently dropped. | I62: Toxiproxy | J62: Alert pipeline | K62: Alerts dropped | L62: Degrade-vs-park decision proven; cron recovery drains parked alerts. | M62: Unenriched/parked alert rate alarmed. | N62: High | O62: — | P62: 3 | Q62: 3 | R62: =P62*Q62 | S62: 2 | W62: Proposed | X62: =IF(P62=5,"Almost Certain",IF(P62=4,"Likely",IF(P62=3,"Possible",IF(P62=2,"Unlikely","Rare")))) | Y62: =IF(R62>=16,"Critical",IF(R62>=9,"High",IF(R62>=4,"Medium","Opportunistic")))
A63: CE-EXT-07 | B63: ChannelContext failure — TE | C63: External Dep | D63: Application | E63: Edge/BFF | F63: TE | G63: Fail ChannelContext calls from TE. | H63: TE renders degraded-but-usable experience (partial data) rather than error page — BFF partial-failure rendering proven. | I63: Toxiproxy | J63: TE UX | K63: Full page failure | L63: Partial-render behavior per widget documented. | M63: Client-visible degradation measured (RUM/synthetic). | N63: High | O63: — | P63: 3 | Q63: 3 | R63: =P63*Q63 | S63: 2 | W63: Proposed | X63: =IF(P63=5,"Almost Certain",IF(P63=4,"Likely",IF(P63=3,"Possible",IF(P63=2,"Unlikely","Rare")))) | Y63: =IF(R63>=16,"Critical",IF(R63>=9,"High",IF(R63>=4,"Medium","Opportunistic")))
A64: CE-EXT-08 | B64: Split.io flag evaluation unavailable | C64: External Dep | D64: Application | E64: All flag users | F64: Per-service inventory | G64: Block Split.io from services. | H64: Each service's fail-open/fail-closed posture per flag is KNOWN and safe; cached/default treatments engage; no feature flapping. | I64: Custom (egress block) | J64: Flag-gated behavior | K64: Unsafe default exposed | L64: Flag-posture inventory produced per service — output is the deliverable. | M64: Flag-evaluation failure visible. | N64: High | O64: — | P64: 2 | Q64: 4 | R64: =P64*Q64 | S64: 2 | W64: Proposed | X64: =IF(P64=5,"Almost Certain",IF(P64=4,"Likely",IF(P64=3,"Possible",IF(P64=2,"Unlikely","Rare")))) | Y64: =IF(R64>=16,"Critical",IF(R64>=9,"High",IF(R64>=4,"Medium","Opportunistic")))
A65: CE-EXT-09 | B65: AuthAnywhere token issuance failure — TE ingress | C65: External Dep | D65: Application | E65: Edge/BFF | F65: TE (API GW token validate) | G65: Degrade AuthAnywhere validation path at TE's edge. | H65: Existing sessions (cached validations) continue per TTL; new sessions fail with clean auth error; no retry storm against IDP. | I65: Custom / coordination | J65: TE ingress auth | K65: Auth retry storm | L65: Session-cache behavior + backoff proven. | M65: Auth-path failure distinct in alerting. | N65: Medium | O65: IDP is shared platform — coordination required; scope to PERF path. | P65: 2 | Q65: 5 | R65: =P65*Q65 | S65: 2 | W65: Proposed | X65: =IF(P65=5,"Almost Certain",IF(P65=4,"Likely",IF(P65=3,"Possible",IF(P65=2,"Unlikely","Rare")))) | Y65: =IF(R65>=16,"Critical",IF(R65>=9,"High",IF(R65>=4,"Medium","Opportunistic")))
A66: CE-CFG-01 | B66: Parameter Store reload failure | C66: Config/Secrets | D66: Application | E66: Event processor | F66: DBE (parameterstore reload strategy) | G66: Block Parameter Store access AFTER startup; then push a config change during the block. | H66: Service continues on last-known-good config (no crash); missed reload is DETECTED; reload resumes on restore without restart. | I66: Custom (deny in PERF) | J66: DBE config | K66: Crash on reload failure | L66: Stale-config runway understood; reload health visible. | M66: Reload-failure alarm exists (suspected gap). | N66: High | O66: — | P66: 2 | Q66: 3 | R66: =P66*Q66 | S66: 2 | W66: Proposed | X66: =IF(P66=5,"Almost Certain",IF(P66=4,"Likely",IF(P66=3,"Possible",IF(P66=2,"Unlikely","Rare")))) | Y66: =IF(R66>=16,"Critical",IF(R66>=9,"High",IF(R66>=4,"Medium","Opportunistic")))
A67: CE-CFG-02 | B67: Secrets retrieval outage at task startup | C67: Config/Secrets | D67: Infrastructure | E67: All | F67: One service per secret pattern | G67: ASM/Secrets Manager outage window + force task recycles during it. | H67: Running tasks unaffected; replacement tasks fail startup FAST and LOUD; crash-loop backoff doesn't mask the root cause; capacity floor alarmed. | I67: Custom (deny) + stop-task | J67: Recycled tasks | K67: Capacity below floor | L67: Startup-dependency blast radius = f(recycle rate during outage) — quantified. | M67: Startup-failure cause attributable in alerts. | N67: High | O67: — | P67: 2 | Q67: 4 | R67: =P67*Q67 | S67: 2 | T67: CE-CACHE-03 | W67: Proposed | X67: =IF(P67=5,"Almost Certain",IF(P67=4,"Likely",IF(P67=3,"Possible",IF(P67=2,"Unlikely","Rare")))) | Y67: =IF(R67>=16,"Critical",IF(R67>=9,"High",IF(R67>=4,"Medium","Opportunistic")))
A68: CE-REG-01 | B68: R53 failover + client re-resolution vs TTL | C68: Region/DR | D68: Infrastructure | E68: Sync API | F68: Active/Passive services | G68: Execute DNS failover; measure ACTUAL client re-resolution against the TTL-floor finding from prior DR work. | H68: Traffic shifts within TTL-derived budget; long-lived connections re-resolve (or are forcibly recycled) per design; no stragglers pinned to failed region. | I68: Drill + client-side measurement | J68: One service's traffic | K68: Stragglers writing to old region | L68: Empirical re-resolution curve vs TTL floor — closes the prior finding. | M68: Traffic-shift completeness measurable per region. | N68: Low | O68: PERF DNS config parity + client population differ — treat as method validation, retest at prod-parity. | P68: 3 | Q68: 4 | R68: =P68*Q68 | S68: 4 | W68: Proposed | X68: =IF(P68=5,"Almost Certain",IF(P68=4,"Likely",IF(P68=3,"Possible",IF(P68=2,"Unlikely","Rare")))) | Y68: =IF(R68>=16,"Critical",IF(R68>=9,"High",IF(R68>=4,"Medium","Opportunistic")))
A69: CE-REG-02 | B69: dr-orchestrator orchestrated failover — full drill | C69: Region/DR | D69: Compound | E69: Orchestrator | F69: dr-orchestrator + one APG scope | G69: Trigger the CloudWatch-alarm-driven orchestrated failover end-to-end (clean-room conditions first). | H69: Orchestrator sequences DNS/DB/service failover correctly; per-step evidence matches design; RTO within target for the scoped APG. | I69: Drill (alarm-triggered) | J69: Scoped APG cross-region | K69: Any step requiring undocumented manual fix | L69: Step-by-step timing evidence; the orchestrator is the system under test. | M69: Orchestrator's own telemetry sufficient to follow progress live. | N69: Medium | O69: dr-orchestrator PERF parity TBC (Open Items). | P69: 2 | Q69: 5 | R69: =P69*Q69 | S69: 4 | T69: CE-DB-06,CE-REG-01 | W69: Proposed | X69: =IF(P69=5,"Almost Certain",IF(P69=4,"Likely",IF(P69=3,"Possible",IF(P69=2,"Unlikely","Rare")))) | Y69: =IF(R69>=16,"Critical",IF(R69>=9,"High",IF(R69>=4,"Medium","Opportunistic")))
A70: CE-REG-03 | B70: Orchestrator impaired DURING failover | C70: Region/DR | D70: Compound | E70: Orchestrator | F70: dr-orchestrator | G70: Fail dr-orchestrator mid-sequence (kill at defined steps). | H70: Partial-failover state is safe (no split-brain), diagnosable, and manually completable from runbook — the orchestrator is not a new SPOF. | I70: Drill + injection | J70: Failover state machine | K70: Split-brain risk | L70: Manual completion path proven per interruption point. | M70: Partial-state visibility explicit. | N70: Medium | O70: Highest-risk drill — schedule with full stakeholder cover. | P70: 1 | Q70: 5 | R70: =P70*Q70 | S70: 4 | T70: CE-REG-02 | W70: Proposed | X70: =IF(P70=5,"Almost Certain",IF(P70=4,"Likely",IF(P70=3,"Possible",IF(P70=2,"Unlikely","Rare")))) | Y70: =IF(R70>=16,"Critical",IF(R70>=9,"High",IF(R70>=4,"Medium","Opportunistic")))
A71: CE-REG-04 | B71: Active/Active brownout (latency-routed) | C71: Region/DR | D71: Infrastructure | E71: Sync API | F71: ALS, ARM | G71: Degrade (not kill) one region — elevated latency/errors below failover thresholds. | H71: Latency-based routing shifts weight gracefully; no oscillation; brownout (gray) handled as well as blackout. | I71: Custom regional degradation | J71: One region's share | K71: Route flapping | L71: Shift + shift-back smooth; hysteresis adequate. | M71: Per-region SLI split visible for A/A services. | N71: Medium | O71: Routing config parity TBC. | P71: 3 | Q71: 4 | R71: =P71*Q71 | S71: 4 | T71: CE-REG-01 | W71: Proposed | X71: =IF(P71=5,"Almost Certain",IF(P71=4,"Likely",IF(P71=3,"Possible",IF(P71=2,"Unlikely","Rare")))) | Y71: =IF(R71>=16,"Critical",IF(R71>=9,"High",IF(R71>=4,"Medium","Opportunistic")))
A72: CE-REG-05 | B72: 3-Active regional loss — experience services | C72: Region/DR | D72: Infrastructure | E72: Edge/BFF | F72: TE, CHE, SSE | G72: Remove one of three regions for stateless experience tier. | H72: Remaining two regions absorb at N+1 capacity; stateless claim proven (no hidden affinity); UX impact ~zero. | I72: Drill | J72: One region of three | K72: UX errors | L72: Hidden-state findings (if any) enumerated. | M72: Tri-region dashboards coherent. | N72: Low | O72: us-west-2 presence in PERF TBC; SSE blocked on documentation. | P72: 2 | Q72: 3 | R72: =P72*Q72 | S72: 4 | T72: CE-EDGE-05 | W72: Proposed | X72: =IF(P72=5,"Almost Certain",IF(P72=4,"Likely",IF(P72=3,"Possible",IF(P72=2,"Unlikely","Rare")))) | Y72: =IF(R72>=16,"Critical",IF(R72>=9,"High",IF(R72>=4,"Medium","Opportunistic")))
A73: CE-REG-06 | B73: MCC Pilot Light activation | C73: Region/DR | D73: Compound | E73: Sync API + pipeline | F73: MCC | G73: Activate MCC's pilot-light DR: stand up capacity, restore data path, cut over. | H73: Activation runbook meets MCC's RTO; ETU scheduled pull resumes in DR region exactly once; S3 config current. | I73: Drill | J73: MCC | K73: RTO blown badly | L73: Pilot-light RTO evidence — different posture, different proof. | M73: DR-region MCC monitored from cold start. | N73: Low | O73: Pilot-light infra existence in PERF TBC (Open Items). | P73: 1 | Q73: 4 | R73: =P73*Q73 | S73: 4 | W73: Proposed | X73: =IF(P73=5,"Almost Certain",IF(P73=4,"Likely",IF(P73=3,"Possible",IF(P73=2,"Unlikely","Rare")))) | Y73: =IF(R73>=16,"Critical",IF(R73>=9,"High",IF(R73>=4,"Medium","Opportunistic")))
A74: CE-REG-07 | B74: Regional failover MID-RECON window | C74: Region/DR | D74: Compound | E74: Recon/pipeline | F74: DTR | G74: Execute regional failover while DTR is mid-run (cross-region S3 + bidirectional Aurora + regional Redis EOD cache). | H74: Recon state survives or safely restarts in DR region: S3 CRR current, Aurora consistent, Redis EOD cache REBUILT from CBS EOD API (it does not replicate). | I74: Drill + timing | J74: EOD recon + region | K74: Posting corrections from inconsistent state | L74: Recon-in-DR completes correct-and-late at worst; Redis rebuild path proven. | M74: Recon-state dashboards exist in BOTH regions. | N74: Medium | O74: Combines CACHE-05 + REG mechanics. | P74: 1 | Q74: 5 | R74: =P74*Q74 | S74: 4 | T74: CE-CACHE-05,CE-REG-02 | W74: Proposed | X74: =IF(P74=5,"Almost Certain",IF(P74=4,"Likely",IF(P74=3,"Possible",IF(P74=2,"Unlikely","Rare")))) | Y74: =IF(R74>=16,"Critical",IF(R74>=9,"High",IF(R74>=4,"Medium","Opportunistic")))
A75: CE-REG-08 | B75: Cross-posture cascade — 3-active edge → failing-over A/P API | C75: Region/DR | D75: Compound | E75: Edge + Sync API | F75: TE/CHE → SAM/AFM path | G75: Regional event where edge tier stays tri-region but its downstream sync APIs are mid-A/P-failover. | H75: Edge retries/timeouts against the failing-over region don't amplify; edge routes to surviving-region API endpoints per discovery design; UX degraded not down. | I75: Drill scenario within REG-02 scope | J75: Edge→API paths | K75: Retry amplification | L75: Posture-mismatch window quantified — unique to your mixed-posture estate. | M75: Cross-region call-path visibility in traces. | N75: Medium | O75: — | P75: 2 | Q75: 4 | R75: =P75*Q75 | S75: 4 | T75: CE-REG-02,CE-APP-03 | W75: Proposed | X75: =IF(P75=5,"Almost Certain",IF(P75=4,"Likely",IF(P75=3,"Possible",IF(P75=2,"Unlikely","Rare")))) | Y75: =IF(R75>=16,"Critical",IF(R75>=9,"High",IF(R75>=4,"Medium","Opportunistic")))
A76: CE-OBS-01 | B76: Detection baseline — Dynatrace coverage & latency | C76: Observability | D76: Detection | E76: All | F76: Wave-1 fault set | G76: For every Wave-1 injection, record: detected? alerted? paged? time-to-detect? correct component blamed? | H76: Dynatrace (SaaS) detects ≥ agreed % of injected faults within target latency with correct root-cause attribution — validating the 'not configured properly' concern with evidence. | I76: Piggyback on Wave-1 runs | J76: n/a | K76: n/a | L76: Coverage/latency scorecard per fault class — THE Wave-1 deliverable for leadership. | M76: This scenario IS the detection criterion. | N76: Medium | O76: Dynatrace config should be env-agnostic — confirm same monitoring config deployed to PERF. | P76: 5 | Q76: 4 | R76: =P76*Q76 | S76: 1 | W76: Proposed | X76: =IF(P76=5,"Almost Certain",IF(P76=4,"Likely",IF(P76=3,"Possible",IF(P76=2,"Unlikely","Rare")))) | Y76: =IF(R76>=16,"Critical",IF(R76>=9,"High",IF(R76>=4,"Medium","Opportunistic")))
A77: CE-OBS-02 | B77: CloudWatch alarm validation — dr-orchestrator triggers | C77: Observability | D77: Detection | E77: Orchestrator | F77: Failover-trigger alarms (owned outside app repos) | G77: Inject the exact conditions each failover-trigger alarm watches; verify firing thresholds/timing. | H77: Every alarm that can trigger orchestrated failover fires when it should and NOT on Wave-1 single-fault noise (false-trigger risk). | I77: Coordination with alarm owners + injection | J77: Alarm set | K77: Accidental failover trigger — HARD ABORT | L77: Trigger-alarm truth table produced; false-positive resistance proven. | M77: n/a (is detection) | N77: Medium | O77: Alarm ownership is external — governance path in Open Items. | P77: 3 | Q77: 5 | R77: =P77*Q77 | S77: 1 | W77: Proposed | X77: =IF(P77=5,"Almost Certain",IF(P77=4,"Likely",IF(P77=3,"Possible",IF(P77=2,"Unlikely","Rare")))) | Y77: =IF(R77>=16,"Critical",IF(R77>=9,"High",IF(R77>=4,"Medium","Opportunistic")))
A78: CE-OBS-03 | B78: Silent-failure probes | C78: Observability | D78: Detection | E78: Event processor / pipeline | F78: DSC warmer stop; DTR purge skip; DBE reload block | G78: Stop things that fail SILENTLY by design shape (no errors, just absence of good behavior). | H78: Absence-of-work is alarmed: warmer heartbeat, purge success metric, reload freshness — or gaps are logged as findings. | I78: Custom per probe | J78: None (observation) | K78: n/a | L78: Silent-failure gap list — expected to be the richest finding source. | M78: n/a (is detection) | N78: High | O78: — | P78: 4 | Q78: 4 | R78: =P78*Q78 | S78: 1 | W78: Proposed | X78: =IF(P78=5,"Almost Certain",IF(P78=4,"Likely",IF(P78=3,"Possible",IF(P78=2,"Unlikely","Rare")))) | Y78: =IF(R78>=16,"Critical",IF(R78>=9,"High",IF(R78>=4,"Medium","Opportunistic")))
A79: CE-OBS-04 | B79: Detection-to-diagnosis drill (on-call) | C79: Observability | D79: Detection | E79: All | F79: On-call rotation | G79: Unannounced (within game-day window) fault; measure alert→ack→correct-diagnosis→correct-runbook time. | H79: Human + tooling loop reaches correct diagnosis within target; runbooks match reality post-Wave-1/2 findings. | I79: Game day | J79: One team's on-call | K79: Distress — abort and debrief | L79: MTTD/MTTI evidence; runbook fixes queued. | M79: n/a (is detection) | N79: High | O79: — | P79: 3 | Q79: 4 | R79: =P79*Q79 | S79: 3 | T79: CE-OBS-01 | W79: Proposed | X79: =IF(P79=5,"Almost Certain",IF(P79=4,"Likely",IF(P79=3,"Possible",IF(P79=2,"Unlikely","Rare")))) | Y79: =IF(R79>=16,"Critical",IF(R79>=9,"High",IF(R79>=4,"Medium","Opportunistic")))
A80: CE-APP-01 | B80: Breaker trip — failure-rate path + half-open recovery | C80: App Resilience | D80: Application | E80: Sync API | F80: Each R4j-protected client (start: CBS clients) | G80: Inject 5xx bursts at/above failure-rate threshold; then heal and observe half-open probing. | H80: Breaker opens at configured rate; fallback engages; half-open probes recover WITHOUT flapping under partial healing. | I80: Toxiproxy / app-level | J80: One client | K80: Flapping open/closed | L80: Config values empirically confirmed per client. | M80: Breaker state transitions visible + alarmed on open. | N80: High | O80: Config-level. | P80: 4 | Q80: 4 | R80: =P80*Q80 | S80: 1 | W80: Proposed | X80: =IF(P80=5,"Almost Certain",IF(P80=4,"Likely",IF(P80=3,"Possible",IF(P80=2,"Unlikely","Rare")))) | Y80: =IF(R80>=16,"Critical",IF(R80>=9,"High",IF(R80>=4,"Medium","Opportunistic")))
A81: CE-APP-02 | B81: Breaker trip — SLOW-CALL-rate path | C81: App Resilience | D81: Application | E81: Sync API | F81: Same clients as APP-01 | G81: Inject latency (no errors) at/above slow-call threshold. | H81: Slow-call breaker path trips — DISTINCT config and code path from failure-rate; services with only failure-rate configured are found now, not in an incident. | I81: Toxiproxy latency | J81: One client | K81: Thread exhaustion | L81: Slow-call config presence/values confirmed per client. | M81: Slow-call breaker events distinguishable from error-trips. | N81: High | O81: — | P81: 4 | Q81: 5 | R81: =P81*Q81 | S81: 1 | T81: CE-APP-01 | W81: Proposed | X81: =IF(P81=5,"Almost Certain",IF(P81=4,"Likely",IF(P81=3,"Possible",IF(P81=2,"Unlikely","Rare")))) | Y81: =IF(R81>=16,"Critical",IF(R81>=9,"High",IF(R81>=4,"Medium","Opportunistic")))
A82: CE-APP-03 | B82: Retry amplification under partial failure | C82: App Resilience | D82: Application | E82: Sync API chain | F82: Multi-hop path (edge→API→CBS) | G82: 30–50% downstream failure rate; observe retry multiplication up the chain. | H82: Retry budgets + jitter + breaker interplay cap amplification ≤ agreed factor; a 30% degradation cannot become 3x load (the classic self-DDoS). | I82: Toxiproxy partial failure | J82: One call chain | K82: Load amplification >2x | L82: Amplification factor per chain measured. | M82: Retry-rate metrics visible per client. | N82: High | O82: — | P82: 4 | Q82: 5 | R82: =P82*Q82 | S82: 1 | T82: CE-APP-01 | W82: Proposed | X82: =IF(P82=5,"Almost Certain",IF(P82=4,"Likely",IF(P82=3,"Possible",IF(P82=2,"Unlikely","Rare")))) | Y82: =IF(R82>=16,"Critical",IF(R82>=9,"High",IF(R82>=4,"Medium","Opportunistic")))
A83: CE-APP-04 | B83: Bulkhead / thread-pool exhaustion | C83: App Resilience | D83: Application | E83: Sync API | F83: One service, multi-dependency | G83: Saturate one dependency's calls; verify OTHER endpoints of the same service stay healthy. | H83: Bulkhead isolation holds: one slow dependency cannot consume the shared thread pool and take down unrelated endpoints. | I83: Toxiproxy + load | J83: One service internals | K83: Unrelated endpoints failing | L83: Isolation proven or bulkhead gap found per service. | M83: Per-pool saturation metrics exposed. | N83: High | O83: — | P83: 3 | Q83: 4 | R83: =P83*Q83 | S83: 2 | T83: CE-APP-02 | W83: Proposed | X83: =IF(P83=5,"Almost Certain",IF(P83=4,"Likely",IF(P83=3,"Possible",IF(P83=2,"Unlikely","Rare")))) | Y83: =IF(R83>=16,"Critical",IF(R83>=9,"High",IF(R83>=4,"Medium","Opportunistic")))
A84: CE-APP-05 | B84: HikariCP pool exhaustion under downstream latency | C84: App Resilience | D84: Application | E84: Sync API | F84: One Aurora-heavy service | G84: Slow DB responses (Toxiproxy on DB path in PERF) until pool saturates. | H84: connectionTimeout fails-fast waiting threads per timeout chain; pool recovers without restart; sizing math validated against thread model. | I84: Toxiproxy on DB path | J84: One service | K84: Hang > chain budget | L84: Pool config empirically validated (input to CE-DB-03). | M84: Pool wait/saturation alarmed before request failures. | N84: High | O84: — | P84: 3 | Q84: 4 | R84: =P84*Q84 | S84: 1 | T84: CE-EDGE-01 | W84: Proposed | X84: =IF(P84=5,"Almost Certain",IF(P84=4,"Likely",IF(P84=3,"Possible",IF(P84=2,"Unlikely","Rare")))) | Y84: =IF(R84>=16,"Critical",IF(R84>=9,"High",IF(R84>=4,"Medium","Opportunistic")))
A85: CE-APP-06 | B85: Heap pressure / GC brownout | C85: App Resilience | D85: Application | E85: Sync API | F85: One JVM service | G85: Gradual memory assault to force sustained GC pressure (not instant OOM — the gray zone). | H85: GC-driven latency degradation is detected and the task is recycled by health checks BEFORE prolonged brownout serving. | I85: Chaos Monkey for Spring Boot memory assault | J85: One task | K85: Brownout > 5 min | L85: Health-check sensitivity to gray degradation proven. | M85: GC/latency correlation alerting exists. | N85: High | O85: — | P85: 3 | Q85: 3 | R85: =P85*Q85 | S85: 2 | T85: CE-COM-07 | W85: Proposed | X85: =IF(P85=5,"Almost Certain",IF(P85=4,"Likely",IF(P85=3,"Possible",IF(P85=2,"Unlikely","Rare")))) | Y85: =IF(R85>=16,"Critical",IF(R85>=9,"High",IF(R85>=4,"Medium","Opportunistic")))
A86: CE-CMP-01 | B86: Writer failover + saturated pools | C86: Compound | D86: Compound | E86: Sync API | F86: SAM + callers | G86: CE-DB-02 under CE-APP-05 preconditions — failover at worst moment. | H86: Combined recovery ≤ FMEA-assessed bound; no deadlock between reconnect storm and pool timeout behavior. | I86: FIS + Toxiproxy + load | J86: Core DB + callers | K86: Brownout > bound | L86: Worst-case failover envelope quantified. | M86: Combined-fault telemetry still attributable. | N86: Low | O86: Capacity-sensitive — directional in PERF. | P86: 2 | Q86: 5 | R86: =P86*Q86 | S86: 3 | T86: CE-DB-02,CE-APP-05 | W86: Proposed | X86: =IF(P86=5,"Almost Certain",IF(P86=4,"Likely",IF(P86=3,"Possible",IF(P86=2,"Unlikely","Rare")))) | Y86: =IF(R86>=16,"Critical",IF(R86>=9,"High",IF(R86>=4,"Medium","Opportunistic")))
A87: CE-CMP-02 | B87: AZ loss during rolling deployment | C87: Compound | D87: Compound | E87: Sync API | F87: One service | G87: CE-NET-02 injected mid-deploy. | H87: min-healthy + AZ rebalance interact safely; deploy halts/rolls back rather than compounding capacity loss. | I87: FIS + pipeline | J87: One service | K87: Capacity < floor | L87: Interaction proven safe. | M87: Operator can distinguish deploy vs AZ signal live. | N87: Medium | O87: — | P87: 2 | Q87: 4 | R87: =P87*Q87 | S87: 3 | T87: CE-NET-02,CE-COM-03 | W87: Proposed | X87: =IF(P87=5,"Almost Certain",IF(P87=4,"Likely",IF(P87=3,"Possible",IF(P87=2,"Unlikely","Rare")))) | Y87: =IF(R87>=16,"Critical",IF(R87>=9,"High",IF(R87>=4,"Medium","Opportunistic")))
A88: CE-CMP-03 | B88: Dependency latency + retry storm cascade | C88: Compound | D88: Compound | E88: Multi-service | F88: Edge→AFM→CBS chain | G88: CBS gray failure (EXT-02) + realistic edge traffic — watch the cascade attempt. | H88: Breakers + retry budgets contain the cascade at first hop; edge sheds gracefully; no cross-APG contagion. | I88: Toxiproxy + load | J88: One journey chain | K88: Contagion beyond chain | L88: Containment proven end-to-end — the marquee compound scenario. | M88: Cascade visible as coherent story in Dynatrace. | N88: Medium | O88: — | P88: 3 | Q88: 5 | R88: =P88*Q88 | S88: 3 | T88: CE-APP-02,CE-APP-03 | W88: Proposed | X88: =IF(P88=5,"Almost Certain",IF(P88=4,"Likely",IF(P88=3,"Possible",IF(P88=2,"Unlikely","Rare")))) | Y88: =IF(R88>=16,"Critical",IF(R88>=9,"High",IF(R88>=4,"Medium","Opportunistic")))
A89: CE-CMP-04 | B89: IDP platform outage — Kafka auth + API OAuth together | C89: Compound | D89: Compound | E89: Cross-cutting | F89: All IDP consumers | G89: Simulate ADFS-IDP unavailable: Kafka OAUTHBEARER (KFK-07) AND TE ingress (EXT-09) simultaneously — IDP is a shared single point. | H89: Session/token caching keeps platform functional for cache lifetime; degradation is gradual and alarmed, not cliff-edge; recovery has no auth stampede. | I89: Custom coordinated block | J89: Platform-wide auth | K89: Cliff-edge failure | L89: IDP blast radius fully mapped — leadership-grade finding either way. | M89: Platform-auth degradation has a single coherent alert story. | N89: Medium | O89: Coordinate scope with platform team. | P89: 2 | Q89: 5 | R89: =P89*Q89 | S89: 3 | T89: CE-KFK-07,CE-EXT-09 | W89: Proposed | X89: =IF(P89=5,"Almost Certain",IF(P89=4,"Likely",IF(P89=3,"Possible",IF(P89=2,"Unlikely","Rare")))) | Y89: =IF(R89>=16,"Critical",IF(R89>=9,"High",IF(R89>=4,"Medium","Opportunistic")))
A90: CE-CMP-05 | B90: Regional failover + cold cache + Aurora capacity | C90: Compound | D90: Compound | E90: All | F90: Surviving region | G90: CE-CACHE-07 amplification during actual regional cutover load shift. | H90: Surviving-region Aurora absorbs (shifted load × cold-cache amplification factor from CACHE-02/04) with headroom. | I90: Drill component within REG scope | J90: Surviving region | K90: Aurora saturation | L90: DR capacity model validated with measured amplification, not assumptions. | M90: Capacity-headroom alarms lead errors. | N90: Low | O90: Capacity-sensitive. | P90: 2 | Q90: 5 | R90: =P90*Q90 | S90: 4 | T90: CE-CACHE-07,CE-REG-02 | W90: Proposed | X90: =IF(P90=5,"Almost Certain",IF(P90=4,"Likely",IF(P90=3,"Possible",IF(P90=2,"Unlikely","Rare")))) | Y90: =IF(R90>=16,"Critical",IF(R90>=9,"High",IF(R90>=4,"Medium","Opportunistic")))
A91: CE-CMP-06 | B91: GAME DAY — region impairment during peak posting window | C91: Compound | D91: Compound | E91: All + Orchestrator | F91: Full journey scope incl. dr-orchestrator, DTR | G91: Full narrative: region degrades during peak activity approaching EOD; alarm-triggered orchestrated failover; recon window at risk; on-call drives. | H91: The PROGRAM's thesis: journeys survive a realistic worst-day with degraded-not-down UX, correct data, recon completing late-but-right, and humans in control throughout. | I91: Game day (all prior tooling) | J91: Full PERF estate | K91: Safety/abort per runbook | L91: End-to-end evidence pack for leadership — the capstone. | M91: Full-stack observability tells one coherent story. | N91: Medium | O91: Capstone — requires Waves 1–3 confirmed. | P91: 1 | Q91: 5 | R91: =P91*Q91 | S91: 4 | T91: CE-REG-02,CE-REG-07,CE-CMP-03,CE-OBS-04 | W91: Proposed | X91: =IF(P91=5,"Almost Certain",IF(P91=4,"Likely",IF(P91=3,"Possible",IF(P91=2,"Unlikely","Rare")))) | Y91: =IF(R91>=16,"Critical",IF(R91>=9,"High",IF(R91>=4,"Medium","Opportunistic")))

Sheet Priority Model
A1: Dimension | B1: Score | C1: Tier / Label | D1: Definition
A2: Likelihood | B2: 5 | C2: Almost Certain | D2: Expected routinely in normal operations (task recycles, single-node events, transient dependency errors).
A3: Likelihood | B3: 4 | C3: Likely | D3: Expected multiple times per year (consumer rebalances, duplicate event delivery, malformed inputs, gray dependency latency).
A4: Likelihood | B4: 3 | C4: Possible | D4: Plausible annually (writer failover, cache failover, AZ impairment, message-broker outage, throttling events).
A5: Likelihood | B5: 2 | C5: Unlikely | D5: Rare but credible (regional service degradation, IAM/KMS policy faults, identity-provider outage, proxy endpoint loss).
A6: Likelihood | B6: 1 | C6: Rare | D6: Exceptional (full region loss, orchestrator failure mid-failover).
A7: Severity | B7: 5 | D7: Data integrity / financial correctness at risk (duplicate writes, incorrect reconciliation, split-brain writes) OR platform-wide outage OR a missed critical processing obligation.
A8: Severity | B8: 4 | D8: Journey outage or major degradation for one or more critical journeys; unrecoverable-without-human events.
A9: Severity | B9: 3 | D9: Single-service degradation with journey-level slowdown; self-healing expected.
A10: Severity | B10: 2 | D10: Localized, transient, absorbed by redundancy; customer-invisible if systems behave.
A11: Severity | B11: 1 | D11: Negligible customer/system impact; hygiene validation.
A12: Priority | B12: L × S | D12: Computed in the catalog (column R) as Likelihood × Severity. Risk Rating (column Y): 16–25 = Critical; 9–15 = High; 4–8 = Medium; 1–3 = Opportunistic.
A13: Wave | B13: 1 | C13: Foundation | D13: Detection baseline + isolated singles with contained blast radius + integrity-critical logic tests (idempotency, dual-trigger, breaker paths, timeout chain).
A14: Wave | B14: 2 | C14: Breadth | D14: Remaining singles across all fault domains; infra faults needing custom tooling; external-dependency injection.
A15: Wave | B15: 3 | C15: Depth | D15: Compounds + coordination-heavy scenarios; on-call drills. Entry: prerequisite singles Confirmed.
A16: Wave | B16: 4 | C16: Capstone | D16: Region/DR drills, orchestrated-failover under test, pilot-light/DR-posture activation, capstone game day. Entry: Waves 1–3 evidence pack + stakeholder sign-off.
A17: Rule | B17: — | D17: A scenario's Wave may never precede any of its Prereq IDs' waves. Likelihood/Severity are proposals — recalibrate against your organization's incident history / FMEA ledger during the FMEA-Ref mapping pass, and again once the code/infra scan (see App & Infra Scan Instructions tabs) produces real evidence.
A19: Likelihood Tier Distribution (live from Scenario Catalog)
A20: Tier | B20: Count
A21: Almost Certain | B21: =COUNTIF('Scenario Catalog'!$X$2:$X$91,A21)
A22: Likely | B22: =COUNTIF('Scenario Catalog'!$X$2:$X$91,A22)
A23: Possible | B23: =COUNTIF('Scenario Catalog'!$X$2:$X$91,A23)
A24: Unlikely | B24: =COUNTIF('Scenario Catalog'!$X$2:$X$91,A24)
A25: Rare | B25: =COUNTIF('Scenario Catalog'!$X$2:$X$91,A25)
A26: Total | B26: =SUM(B21:B25)
A29: Risk Rating Distribution (live from Scenario Catalog)
A30: Rating | B30: Count
A31: Critical | B31: =COUNTIF('Scenario Catalog'!$Y$2:$Y$91,A31)
A32: High | B32: =COUNTIF('Scenario Catalog'!$Y$2:$Y$91,A32)
A33: Medium | B33: =COUNTIF('Scenario Catalog'!$Y$2:$Y$91,A33)
A34: Opportunistic | B34: =COUNTIF('Scenario Catalog'!$Y$2:$Y$91,A34)
A35: Total | B35: =SUM(B31:B34)

Sheet Wave Plan
A1: Wave | B1: Theme | C1: Entry Criteria | D1: Exit Criteria | E1: # Scenarios (live) | F1: Sum Priority (live)
A2: 1 | B2: Detection baseline + contained singles + integrity logic (idempotency, dual-trigger, breaker both paths, timeout chain, DSM state, recon restart) | C2: PERF load harness ready; FIS onboarded; Dynatrace/CloudWatch access for evidence capture; game-day runbook + abort authority named. | D2: ≥80% of Wave-1 scenarios Executed; detection scorecard (CE-OBS-01) published; findings triaged into FMEA ledger; steady-state gaps listed. | E2: =COUNTIF('Scenario Catalog'!$S$2:$S$91,A2) | F2: =SUMIF('Scenario Catalog'!$S$2:$S$91,A2,'Scenario Catalog'!$R$2:$R$91)
A3: 2 | B3: Full single-fault breadth: data/cache/kafka/pipeline/network/edge/external/config | C3: Wave-1 exit met; custom tooling built (Toxiproxy layer, IAM/KMS/ASM deny scripts, file injectors, event suppressors); FIS Fargate network actions confirmed or tc-fallback ready. | D3: All fault domains have ≥1 Confirmed scenario; per-service resilience-config truth table (breaker/retry/pool) published. | E3: =COUNTIF('Scenario Catalog'!$S$2:$S$91,A3) | F3: =SUMIF('Scenario Catalog'!$S$2:$S$91,A3,'Scenario Catalog'!$R$2:$R$91)
A4: 3 | B4: Compounds, cascades, on-call drills | C4: Prereq singles Confirmed; blast-radius model per compound approved; alarm owners engaged (CE-OBS-02 done). | D4: Compound envelope evidence (failover-under-saturation, cascade containment, IDP blast radius); MTTD/MTTI baseline from drills. | E4: =COUNTIF('Scenario Catalog'!$S$2:$S$91,A4) | F4: =SUMIF('Scenario Catalog'!$S$2:$S$91,A4,'Scenario Catalog'!$R$2:$R$91)
A5: 4 | B5: Region/DR: R53, orchestrated failover, orchestrator-under-test, pilot light, mid-recon failover, capstone game day | C5: Waves 1–3 evidence pack; leadership sign-off; dr-orchestrator PERF parity confirmed; rollback/abort rehearsed. | D5: RTO/RPO evidence per DR posture (A/A, A/P, 3-Active, Pilot Light); capstone game-day report — the program's leadership deliverable. | E5: =COUNTIF('Scenario Catalog'!$S$2:$S$91,A5) | F5: =SUMIF('Scenario Catalog'!$S$2:$S$91,A5,'Scenario Catalog'!$R$2:$R$91)
B6: TOTAL | E6: =SUM(E2:E5)

Sheet Coverage Matrix
A1: Scenario counts by Fault Domain × Wave (live from catalog)
A2: Fault Domain | B2: Wave 1 | C2: Wave 2 | D2: Wave 3 | E2: Wave 4 | F2: Total
A3: Compute | B3: =COUNTIFS('Scenario Catalog'!$C$2:$C$91,$A3,'Scenario Catalog'!$S$2:$S$91,1) | C3: =COUNTIFS('Scenario Catalog'!$C$2:$C$91,$A3,'Scenario Catalog'!$S$2:$S$91,2) | D3: =COUNTIFS('Scenario Catalog'!$C$2:$C$91,$A3,'Scenario Catalog'!$S$2:$S$91,3) | E3: =COUNTIFS('Scenario Catalog'!$C$2:$C$91,$A3,'Scenario Catalog'!$S$2:$S$91,4) | F3: =SUM(B3:E3)
A4: Resource | B4: =COUNTIFS('Scenario Catalog'!$C$2:$C$91,$A4,'Scenario Catalog'!$S$2:$S$91,1) | C4: =COUNTIFS('Scenario Catalog'!$C$2:$C$91,$A4,'Scenario Catalog'!$S$2:$S$91,2) | D4: =COUNTIFS('Scenario Catalog'!$C$2:$C$91,$A4,'Scenario Catalog'!$S$2:$S$91,3) | E4: =COUNTIFS('Scenario Catalog'!$C$2:$C$91,$A4,'Scenario Catalog'!$S$2:$S$91,4) | F4: =SUM(B4:E4)
A5: Data-Aurora | B5: =COUNTIFS('Scenario Catalog'!$C$2:$C$91,$A5,'Scenario Catalog'!$S$2:$S$91,1) | C5: =COUNTIFS('Scenario Catalog'!$C$2:$C$91,$A5,'Scenario Catalog'!$S$2:$S$91,2) | D5: =COUNTIFS('Scenario Catalog'!$C$2:$C$91,$A5,'Scenario Catalog'!$S$2:$S$91,3) | E5: =COUNTIFS('Scenario Catalog'!$C$2:$C$91,$A5,'Scenario Catalog'!$S$2:$S$91,4) | F5: =SUM(B5:E5)
A6: Cache | B6: =COUNTIFS('Scenario Catalog'!$C$2:$C$91,$A6,'Scenario Catalog'!$S$2:$S$91,1) | C6: =COUNTIFS('Scenario Catalog'!$C$2:$C$91,$A6,'Scenario Catalog'!$S$2:$S$91,2) | D6: =COUNTIFS('Scenario Catalog'!$C$2:$C$91,$A6,'Scenario Catalog'!$S$2:$S$91,3) | E6: =COUNTIFS('Scenario Catalog'!$C$2:$C$91,$A6,'Scenario Catalog'!$S$2:$S$91,4) | F6: =SUM(B6:E6)
A7: Messaging-Kafka | B7: =COUNTIFS('Scenario Catalog'!$C$2:$C$91,$A7,'Scenario Catalog'!$S$2:$S$91,1) | C7: =COUNTIFS('Scenario Catalog'!$C$2:$C$91,$A7,'Scenario Catalog'!$S$2:$S$91,2) | D7: =COUNTIFS('Scenario Catalog'!$C$2:$C$91,$A7,'Scenario Catalog'!$S$2:$S$91,3) | E7: =COUNTIFS('Scenario Catalog'!$C$2:$C$91,$A7,'Scenario Catalog'!$S$2:$S$91,4) | F7: =SUM(B7:E7)
A8: Pipeline-Recon | B8: =COUNTIFS('Scenario Catalog'!$C$2:$C$91,$A8,'Scenario Catalog'!$S$2:$S$91,1) | C8: =COUNTIFS('Scenario Catalog'!$C$2:$C$91,$A8,'Scenario Catalog'!$S$2:$S$91,2) | D8: =COUNTIFS('Scenario Catalog'!$C$2:$C$91,$A8,'Scenario Catalog'!$S$2:$S$91,3) | E8: =COUNTIFS('Scenario Catalog'!$C$2:$C$91,$A8,'Scenario Catalog'!$S$2:$S$91,4) | F8: =SUM(B8:E8)
A9: Network | B9: =COUNTIFS('Scenario Catalog'!$C$2:$C$91,$A9,'Scenario Catalog'!$S$2:$S$91,1) | C9: =COUNTIFS('Scenario Catalog'!$C$2:$C$91,$A9,'Scenario Catalog'!$S$2:$S$91,2) | D9: =COUNTIFS('Scenario Catalog'!$C$2:$C$91,$A9,'Scenario Catalog'!$S$2:$S$91,3) | E9: =COUNTIFS('Scenario Catalog'!$C$2:$C$91,$A9,'Scenario Catalog'!$S$2:$S$91,4) | F9: =SUM(B9:E9)
A10: Edge | B10: =COUNTIFS('Scenario Catalog'!$C$2:$C$91,$A10,'Scenario Catalog'!$S$2:$S$91,1) | C10: =COUNTIFS('Scenario Catalog'!$C$2:$C$91,$A10,'Scenario Catalog'!$S$2:$S$91,2) | D10: =COUNTIFS('Scenario Catalog'!$C$2:$C$91,$A10,'Scenario Catalog'!$S$2:$S$91,3) | E10: =COUNTIFS('Scenario Catalog'!$C$2:$C$91,$A10,'Scenario Catalog'!$S$2:$S$91,4) | F10: =SUM(B10:E10)
A11: External Dep | B11: =COUNTIFS('Scenario Catalog'!$C$2:$C$91,$A11,'Scenario Catalog'!$S$2:$S$91,1) | C11: =COUNTIFS('Scenario Catalog'!$C$2:$C$91,$A11,'Scenario Catalog'!$S$2:$S$91,2) | D11: =COUNTIFS('Scenario Catalog'!$C$2:$C$91,$A11,'Scenario Catalog'!$S$2:$S$91,3) | E11: =COUNTIFS('Scenario Catalog'!$C$2:$C$91,$A11,'Scenario Catalog'!$S$2:$S$91,4) | F11: =SUM(B11:E11)
A12: Config/Secrets | B12: =COUNTIFS('Scenario Catalog'!$C$2:$C$91,$A12,'Scenario Catalog'!$S$2:$S$91,1) | C12: =COUNTIFS('Scenario Catalog'!$C$2:$C$91,$A12,'Scenario Catalog'!$S$2:$S$91,2) | D12: =COUNTIFS('Scenario Catalog'!$C$2:$C$91,$A12,'Scenario Catalog'!$S$2:$S$91,3) | E12: =COUNTIFS('Scenario Catalog'!$C$2:$C$91,$A12,'Scenario Catalog'!$S$2:$S$91,4) | F12: =SUM(B12:E12)
A13: Region/DR | B13: =COUNTIFS('Scenario Catalog'!$C$2:$C$91,$A13,'Scenario Catalog'!$S$2:$S$91,1) | C13: =COUNTIFS('Scenario Catalog'!$C$2:$C$91,$A13,'Scenario Catalog'!$S$2:$S$91,2) | D13: =COUNTIFS('Scenario Catalog'!$C$2:$C$91,$A13,'Scenario Catalog'!$S$2:$S$91,3) | E13: =COUNTIFS('Scenario Catalog'!$C$2:$C$91,$A13,'Scenario Catalog'!$S$2:$S$91,4) | F13: =SUM(B13:E13)
A14: Observability | B14: =COUNTIFS('Scenario Catalog'!$C$2:$C$91,$A14,'Scenario Catalog'!$S$2:$S$91,1) | C14: =COUNTIFS('Scenario Catalog'!$C$2:$C$91,$A14,'Scenario Catalog'!$S$2:$S$91,2) | D14: =COUNTIFS('Scenario Catalog'!$C$2:$C$91,$A14,'Scenario Catalog'!$S$2:$S$91,3) | E14: =COUNTIFS('Scenario Catalog'!$C$2:$C$91,$A14,'Scenario Catalog'!$S$2:$S$91,4) | F14: =SUM(B14:E14)
... A16: Compound | B16: =COUNTIFS('Scenario Catalog'!$C$2:$C$91,$A16,'Scenario Catalog'!$S$2:$S$91,1) | C16: =COUNTIFS('Scenario Catalog'!$C$2:$C$91,$A16,'Scenario Catalog'!$S$2:$S$91,2) | D16: =COUNTIFS('Scenario Catalog'!$C$2:$C$91,$A16,'Scenario Catalog'!$S$2:$S$91,3) | E16: =COUNTIFS('Scenario Catalog'!$C$2:$C$91,$A16,'Scenario Catalog'!$S$2:$S$91,4) | F16: =SUM(B16:E16)
A17: TOTAL | B17: =SUM(B3:B16) | C17: =SUM(C3:C16) | D17: =SUM(D3:D16) | E17: =SUM(E3:E16) | F17: =SUM(F3:F16)
A19: Scenario counts by Injection Plane
A20: Injection Plane | B20: Count
A21: Infrastructure | B21: =COUNTIF('Scenario Catalog'!$D$2:$D$91,A21)
A22: Application | B22: =COUNTIF('Scenario Catalog'!$D$2:$D$91,A22)
A23: Compound | B23: =COUNTIF('Scenario Catalog'!$D$2:$D$91,A23)
A24: Detection | B24: =COUNTIF('Scenario Catalog'!$D$2:$D$91,A24)
A25: TBD | B25: =COUNTIF('Scenario Catalog'!$D$2:$D$91,A25)

Sheet Open Items
A1: # | B1: Item | C1: Why it matters / what it gates | D1: Owner | E1: Status
A2: 1 | B2: RDS Proxy split confirmation | C2: Diagram silence ≠ proof of direct connection (per your table's own caveat). CE-DB-01/02 asymmetry design assumes proxy = DCM/DBE/DTE only. Enrique checking. | D2: Enrique | E2: Open
A3: 2 | B3: FMEA Ref mapping | C3: Map all 90 scenarios to existing FMEA scenario IDs (ASSESSED items first). Recalibrate L/S scores against ledger values during the pass. | D3: Chaos team | E3: Open
A4: 3 | B4: Journey mapping | C4: Populate Journeys column against the official 16-journey list; journey criticality then feeds wave-1 sub-ordering. | D4: Chaos team | E4: Open
A5: 4 | B5: Dynatrace PERF config parity | C5: 'Team hasn't configured things properly' — CE-OBS-01 validates coverage, but first confirm the SAME monitoring config is deployed to PERF, else the scorecard measures the wrong thing. | D5: Chaos + Obs team | E5: Open
A6: 5 | B6: PERF↔PROD delta register | C6: Formal list: task counts/scaling, Aurora instance classes, data volumes, us-west-2 presence for 3-Active tier, pilot-light infra for MCC, R53/DNS config, dr-orchestrator parity, timeout config parity. Every 'Medium/Low PERF validity' flag resolves against this register. | D6: Enrique + Chaos team | E6: Open
A7: 6 | B7: FIS Fargate network actions availability | C7: Latency/loss/blackhole on Fargate needs fault-injection endpoints + pidMode:task and no blocking SCPs. If unavailable → build tc-sidecar fallback (gates CE-NET-01/02). | D7: Chaos team | E7: Open
A8: 7 | B8: External-dependency injection layer | C8: Decide and build the Toxiproxy (or equivalent) layer in front of dedicated PERF CBS + LCDP/CSU/ChannelContext paths. PERF CBS is live — inject in front, never break it. Gates all CE-EXT. | D8: Chaos team | E8: Open
A9: 8 | B9: CloudWatch alarm ownership | C9: Failover-trigger alarms owned outside app repos — CE-OBS-02 requires their owners at the table; false-trigger risk makes this a governance item, not a courtesy. | D9: Enrique | E9: Open
A10: 9 | B10: Spend-Track documentation | C10: No artifact exists. All SSE scenarios blocked until minimum documentation lands. Finding in itself. | D10: Service team | E10: Blocked
A11: 10 | B11: DLAT dependency documentation | C11: Infra-only diagram; CE-EDGE-06 doubles as the discovery exercise. | D11: Service team | E11: Open
A12: 11 | B12: Kafka SaaS placeholder | C12: CE-KFK-09 reserved. Re-plan KFK family when platform is selected. Per direction: no planning now. | D12: — | E12: Parked
A13: 12 | B13: VPC endpoint architecture | C13: Confirm PrivateLink/endpoint usage before CE-NET-04 is scoped. | D13: Enrique | E13: Open
... A15: 14 | B15: Steady-state SLI gaps | C15: Any Wave-1 scenario without a trusted steady-state signal gets logged here and becomes an observability work item before execution. | D15: Chaos team | E15: Standing

Sheet App Scan Instructions
A1: Application Code Scan — Method & Standard
A2: Durable reference for scanning ANY application repo for chaos-relevant, resilience-relevant facts. Written to be re-run unchanged on new services built after this catalog. Applies to Maven multi-module repos (root/parent pom.xml + one pom.xml per module) by default — adapt the build-file parsing step for other build tools.
A4: Non-negotiable rules (apply to every category below)
A5: • Every extracted fact carries evidence: {file path, line number, verbatim snippet}. No fact without evidence.
A6: • Never assume a framework default. If a value isn't explicitly configured, record NOT_CONFIGURED — <library>@<version> default in effect and name the version; do not state what that default is unless verified against that exact version's documentation, and mark it a human-verify item if stated.
A7: • A value only resolvable through Maven property inheritance or a profile-activated override that cannot be statically traced is AMBIGUOUS, with both candidate values and their sources recorded — never silently pick one.
A8: • Config sourced from Secrets Manager / Parameter Store / VaultSM-ASM-style vaults (i.e., the key exists in code but the value is externally resolved) is EXTERNAL_CONFIG — not resolvable from repo. Do not attempt to guess the resolved value.
A9: • A category with genuinely nothing found is NOT_FOUND, with the search patterns used listed — a clean sheet is a finding, not a skipped row.
A10: • Status vocabulary is exactly: CONFIRMED | NOT_FOUND | NOT_CONFIGURED | AMBIGUOUS | EXTERNAL_CONFIG | NOT_APPLICABLE. Do not invent new statuses.
A12: Scan categories
A13: Category | B13: What to Extract | C13: Where to Look (signals / patterns) | D13: Evidence to Capture | E13: Feeds Fault Domain(s) / Scenario Family
A14: Dependency & Version Census | B14: Build tool, resolved versions of: Spring Boot, Resilience4j, Feign/OpenFeign, HikariCP, Kafka client, AWS SDK (v1/v2), RDS/Aurora JDBC driver (aws-jdbc-wrapper or plain), Redis client. Version pins what a 'default' even means. | C14: Root/parent pom.xml <properties>/<dependencyManagement>; each module pom.xml; run `mvn help:effective-pom` if Maven+JDK available on the scanning host for guaranteed resolution, else static multi-file parsing (mark inherited-but-unresolved properties AMBIGUOUS). | D14: artifactId, resolved version, resolution method (effective-pom vs static), source file(s). | E14: Feeds every other category below — versions gate what 'not configured' means.
A15: Resilience Config (circuit breakers, retry, bulkhead) | B15: Every @CircuitBreaker/@Retry/@Bulkhead/@RateLimiter annotation (or programmatic Resilience4j registry config): instance name, failureRateThreshold, slowCallRateThreshold + slowCallDurationThreshold, waitDurationInOpenState, permittedNumberOfCallsInHalfOpenState, whether a fallbackMethod actually exists and its signature matches, retry maxAttempts/backoff/jitter, bulkhead maxConcurrentCalls. | C15: @CircuitBreaker/@Retry/@Bulkhead/@RateLimiter annotations; resilience4j.* keys in application*.yml; any programmatic CircuitBreakerConfig/RetryConfig builders. | D15: Per protected call: client/method name, every configured threshold with file:line, presence/absence of slow-call config specifically (most common gap), fallback method existence. | E15: App Resilience family (breaker/retry/bulkhead scenarios); directly assigns targets for slow-call-path experiments.
A16: Timeout Chain (app-side) | B16: Every timeout value in the request path: HikariCP connectionTimeout/maxLifetime/idleTimeout, Feign/RestTemplate/WebClient connect+read timeouts, Resilience4j TimeLimiter duration, Kafka request.timeout.ms/session.timeout.ms. | C16: application*.yml under spring.datasource.hikari.*, feign.client.config.*, resilience4j.timelimiter.*, spring.kafka.*; RestTemplateBuilder/WebClient.Builder construction sites (flag any built with NO explicit timeout — infinite by default). | D16: Layer name, key, value, unit, file:line. Explicitly flag any HTTP client built without a timeout. | E16: Edge / timeout-chain-ordering scenarios; cross-referenced against infra-side ALB/NLB/API-GW timeouts in the Timeout Chain sheet.
A17: Retry Amplification Inputs | B17: For each outbound call in a chain, its retry count and backoff — used to compute worst-case multiplicative amplification across a multi-hop path. | C17: Same annotations as Resilience Config, organized by caller→callee edges (derive edges from Feign client interfaces / RestTemplate call sites / method names matching known downstream services). | D17: Caller, callee, retry count, backoff type. The consolidation script multiplies retry counts along a path — do not compute the product yourself in the scan; just report the edges. | E17: App Resilience — retry-storm / self-inflicted-load scenarios.
A18: Kafka Consumer / Producer Config | B18: Per @KafkaListener or consumer factory: auto.offset.reset, enable.auto.commit (vs manual ack), max.poll.interval.ms vs realistic processing time, presence of an error handler / DLQ wiring, container-level concurrency. Per producer: acks, idempotence setting, retries. | C18: @KafkaListener annotations and their consumer factory beans; application*.yml spring.kafka.consumer.*/producer.*; DefaultErrorHandler / SeekToCurrentErrorHandler / dead-letter-publishing-recoverer usage. | D18: Listener method, topic, group id, each setting with file:line. Flag auto.offset.reset=latest on any consumer whose group appears durable/stateful (candidate for silent message loss). | E18: Messaging/Kafka family — poison-message, duplicate-delivery, rebalance, and offset-loss scenarios.
A19: Idempotency Evidence | B19: For each event handler and file-ingestion write path: does the write show idempotency machinery (upsert / ON CONFLICT / merge, a dedup or processed-event-id table, natural-key uniqueness constraint) or a bare insert/save with no guard? | C19: Repository/DAO save methods invoked from @KafkaListener or file-processing code paths; JPA @Table unique constraints; native SQL with ON CONFLICT/MERGE; any 'seen event id' check. | D19: Handler name, evidence type found (or NONE_FOUND), file:line, a suspicion_level of low/medium/high (NONE_FOUND = high suspicion — cannot prove idempotency statically, only rank it). | E19: Duplicate-delivery and pipeline-restart-idempotency scenarios — ranks which consumers to test first.
A20: Anti-Pattern Sweep | B20: Broad-catch exception swallowing around remote calls; unbounded thread pools / @Async without a bounded executor; hardcoded Thread.sleep in retry logic; HTTP clients built with no timeout (cross-ref with Timeout Chain); blocking calls inside a Kafka listener thread; multi-write event handlers without a transaction boundary. | C20: grep/ripgrep for catch (Exception, catch (Throwable, Thread.sleep(, new RestTemplate() / WebClient.builder().build() with no timeout call chained, @Async without a named bounded executor bean, @KafkaListener methods calling blocking I/O without async offload. Semgrep rules are an optional accelerator if installable; otherwise pattern-match plus a read of the surrounding method for confirmation before flagging. | D20: Pattern id, description, file:line, snippet, a plain-language severity_hint (not a formal score — that stays human judgment). | E20: Generates candidate NEW scenarios beyond the current 90 — this category is expected to surface gaps, not just confirm existing ones.
A21: Spring Profile Inventory | B21: Every environment profile present (perf, prod, and any others) and every config file / config-file-per-profile that exists for it. | C21: application.yml plus application-<profile>.yml per module; @Profile annotations in code; any profile-conditional @Bean. | D21: Profile name, config file path(s), any profile-gated bean/behavior found in code (not just config). | E21: Feeds the Profile Diff step below directly.
A23: Profile Diff — perf vs prod
A24: • For every config key found in the Spring Profile Inventory, resolve the EFFECTIVE value per profile (base application.yml overridden by application-<profile>.yml — do not stop at the base file).
A25: • Diff perf vs prod key-by-key. Classify each difference as: expected (endpoints, hostnames, credential references, log levels) or suspicious (timeouts, pool sizes, retry counts, breaker thresholds, batch sizes, thread-pool sizes differing across environments — anything that changes SYSTEM BEHAVIOR, not just its target).
A26: • A key present in one profile file and silently absent in the other is its own finding (missing_in_one) — do not assume it 'falls back to base' without confirming the override mechanism actually works that way for that key.
A27: • Output feeds the Profile Mismatch Register sheet and directly resolves 'PERF Validity' flags already in the Scenario Catalog — a scenario marked Medium/Low PERF validity should point at the specific suspicious diff that causes the caveat.
A30: Keeping this current
A31: • New service repo added: run the full category list against it once at onboarding; add its row to the Service Inventory tab; propose new scenario IDs following the CE-<DOMAIN>-NN convention for any pattern not already covered.
A32: • New dependency/library adopted (e.g., a new HTTP client, a new messaging library): add a row to this table before the next scan cycle — this table should grow with your stack, not silently miss new tech.
A33: • Re-run cadence: re-scan after any change to resilience/timeout/Kafka config, and at minimum once per quarter to catch drift — config drift between scans is itself a finding worth tracking.

Sheet Infra Scan Instructions
A1: Infrastructure Scan — Method & Standard
A2: Durable reference for discovering and cataloging cloud components from infrastructure-as-code repos, and for keeping the Service Inventory tab and the fault-domain taxonomy current as the architecture evolves. Tool-agnostic by design — detect the IaC tool in use per repo rather than assuming one.
A4: Non-negotiable rules (same as the App tab)
A5: • Every extracted fact carries evidence: {file path, line number / resource block, verbatim snippet}.
A6: • Never assume a cloud-provider default for an unset attribute — record NOT_CONFIGURED and name the provider/resource-type default only if you can point to its source (provider docs version), otherwise leave it for human verification.
A7: • A value set via a variable/module input that isn't resolvable without running the tool (terraform plan, cdk synth) is AMBIGUOUS with the variable name and every default/tfvars candidate recorded.
A8: • Status vocabulary matches the App tab exactly: CONFIRMED | NOT_FOUND | NOT_CONFIGURED | AMBIGUOUS | EXTERNAL_CONFIG | NOT_APPLICABLE.
A10: Step 1 — Detect the IaC tool (per repo, do not assume)
A11: Signal file(s) | B11: Tool | C11: Primary extraction approach
A12: *.tf, *.tf.json, terraform.tfstate* | B12: Terraform | C12: Parse HCL resource blocks directly for CONFIRMED values; if `terraform` CLI is available, `terraform show -json` on a plan gives fully resolved values and should be preferred over static HCL parsing where variables are involved.
A13: cdk.json + *.ts/*.py CDK constructs | B13: AWS CDK | C13: Static analysis of construct props is best-effort only — CDK constructs apply implicit defaults in code, not in the file you're reading. If `cdk synth` can be run, extract from the synthesized CloudFormation template instead for CONFIRMED-grade values.
A14: template.yaml/json with AWSTemplateFormatVersion, or SAM's template.yaml | B14: CloudFormation / SAM | C14: Parse Resources: block directly — declarative, closest to ground truth without needing to execute anything.
A15: serverless.yml | B15: Serverless Framework | C15: Parse provider:/functions:/resources: blocks; note this framework often layers its own defaults atop the CloudFormation it generates — flag accordingly.
A16: None of the above found | B16: Unknown / manual provisioning | C16: Mark the repo NOT_APPLICABLE for automated extraction and log it in Open Items — infrastructure may be console/ClickOps-managed, which is itself a finding worth surfacing to leadership.
A18: Step 2 — Component categories to extract
A19: Component Category | B19: Resource Types / Signals | C19: What to Extract | D19: Cross-Check Against | E19: Feeds Fault Domain(s)
A20: Compute | B20: ECS Service + TaskDefinition (or equivalent: EKS, Lambda, EC2 ASG) | C20: Launch type (Fargate/EC2), desired count, min/max healthy percent during deploy, CPU/memory, whether env vars override any app-side config (this is a common silent divergence from the checked-in application.yml). | D20: App Scan census — flag any env-var override of a value the App scan also found in code, both values recorded. | E20: Compute
A21: Data store | B21: RDS/Aurora cluster + instance, RDS Proxy, DynamoDB table | C21: Engine + version, instance class, Multi-AZ, Aurora Global Database membership + failover priority/region roles, whether an RDS Proxy resource exists and which services' security groups/target groups point at it (this is how you CONFIRM the proxy-vs-direct split rather than inferring it from an app diagram). | D21: Service Inventory tab's 'RDS Proxy' column — reconcile any disagreement rather than picking one source silently. | E21: Data-Aurora / Data-<other>
A22: Cache | B22: ElastiCache replication group / cluster | C22: Engine (Redis/Memcached), node type, Multi-AZ, number of shards/replicas, auth-token requirement, per-region vs shared cluster topology. | D22: App Scan's client config for connection/auth patterns. | E22: Cache
A23: Messaging / broker | B23: MSK cluster, self-managed broker security groups, or SaaS broker network path (VPC peering/PrivateLink to a message-broker SaaS) | C23: Broker type, number of brokers/AZs, encryption-in-transit setting, auth mechanism (SASL/mTLS/IAM), network path (on-prem via Direct Connect vs in-VPC vs SaaS over PrivateLink). | D23: App Scan's Kafka consumer/producer config category. | E23: Messaging
A24: Edge / ingress | B24: ALB, NLB, API Gateway (REST or HTTP API), Route 53 records + routing policy | C24: Idle timeout (ALB default 60s / commonly raised; NLB default varies), deregistration delay, API Gateway throttle burst/rate limit and integration timeout (hard cap on managed API Gateway), Route 53 routing policy (failover/latency/weighted) + TTL. | D24: App Scan's Timeout Chain category — THIS is the piece that closes the loop between app-declared timeouts and the infra ceiling around them. | E24: Edge / timeout-chain-ordering
A25: Async / eventing | B25: SQS queue + redrive policy/DLQ, EventBridge rule + schedule expression, SNS topic, Lambda function + concurrency/reserved-concurrency, S3 event notifications | C25: Queue visibility timeout vs consumer processing time, DLQ maxReceiveCount, EventBridge schedule expression + target, Lambda reserved concurrency (a throttling ceiling that can silently cap a 'scheduled job' pattern). | D25: App Scan's scheduled-job findings (duplicate/missed execution risk) — infra concurrency limits are often the actual root cause. | E25: Compute (scheduled) / Pipeline
A26: Secrets & config | B26: Secrets Manager secret, SSM Parameter Store parameter, KMS key + key policy | C26: Rotation configuration (automatic vs none), which IAM roles/policies grant access, KMS key policy grantees, whether a parameter uses SecureString. | D26: App Scan's EXTERNAL_CONFIG-flagged keys — this is where those get their access-pattern facts filled in (not their values). | E26: Config/Secrets
A27: Network boundary | B27: VPC endpoints (Interface/Gateway), Direct Connect / Transit Gateway attachments, security groups on cross-boundary paths | C27: Which AWS services have a private endpoint vs traverse NAT/public path; on-prem-bound routes and what depends on them. | D27: App Scan's on-prem/external-dependency findings. | E27: Network
A28: DR / region posture | B28: Aurora Global Database region config, Route 53 failover records, any DR-orchestration resource (state machine, custom automation, alarm-triggered Lambda/pipeline) | C28: Per-service DR posture as CONFIRMED infra fact (active/active, active/passive, N-active, pilot light) rather than as previously diagrammed/reported — infra is ground truth here. | D28: Service Inventory tab's DR Posture column — reconcile disagreements explicitly. | E28: Region/DR
A30: Step 3 — Reconciling infra facts against the Service Inventory tab
A31: • The Service Inventory tab was originally built from architecture diagrams — treat infra-as-code as the higher-confidence source when the two disagree, but record BOTH values and the disagreement rather than silently overwriting the diagram-derived one.
A32: • Any component found in infra that has no corresponding row/mention in Service Inventory is a coverage gap — add it rather than dropping it.
A33: • RDS Proxy presence/absence is the single highest-value reconciliation in this pass — several catalog scenarios (e.g., writer-failover asymmetry) depend on it being correct.
A36: Onboarding a new AWS component or service (future-proofing)
A37: • 1. Add a row to the Step-2 table above: component category, resource types/signals, what to extract, what to cross-check.
A38: • 2. Decide which existing Fault Domain (Coverage Matrix tab in the main workbook) it belongs to, or declare a new one if genuinely novel.
A39: • 3. Draft at least one new scenario using the existing ID convention: CE-<DOMAIN>-NN, with the same required fields as the Scenario Catalog tab (hypothesis, tooling, blast radius, abort condition, dual success criteria, PERF validity).
A40: • 4. Add the component to the Service Inventory tab for every service that adopts it, not just the first one.
